{"inputConfig":{"gcsSource":{"uri":"gs://iiith-ska-satamt/ocr/src/ramagitai/ramagitai.pdf"},"mimeType":"application/pdf"},"responses":[{"fullTextAnnotation":{"pages":[{"property":{"detectedLanguages":[{"languageCode":"ta","confidence":0.78184843},{"languageCode":"sa","confidence":0.21427743}]},"width":396,"height":468,"blocks":[{"boundingBox":{"normalizedVertices":[{"x":0.17929293,"y":0.12820514},{"x":0.18181819,"y":0.12820514},{"x":0.18181819,"y":0.13247864},{"x":0.17929293,"y":0.13247864}]},"paragraphs":[{"boundingBox":{"normalizedVertices":[{"x":0.17929293,"y":0.12820514},{"x":0.18181819,"y":0.12820514},{"x":0.18181819,"y":0.13247864},{"x":0.17929293,"y":0.13247864}]},"words":[{"boundingBox":{"normalizedVertices":[{"x":0.17929293,"y":0.12820514},{"x":0.18181819,"y":0.12820514},{"x":0.18181819,"y":0.13247864},{"x":0.17929293,"y":0.13247864}]},"symbols":[{"property":{"detectedBreak":{"type":"LINE_BREAK"}},"text":":","confidence":0.6584301}],"confidence":0.6584301}],"confidence":0.6584301}],"blockType":"TEXT","confidence":0.6584301},{"boundingBox":{"normalizedVertices":[{"x":0.4318182,"y":0.115384616},{"x":0.57828283,"y":0.113247864},{"x":0.57828283,"y":0.1431624},{"x":0.4318182,"y":0.14529915}]},"paragraphs":[{"boundingBox":{"normalizedVertices":[{"x":0.4318182,"y":0.115384616},{"x":0.57828283,"y":0.113247864},{"x":0.57828283,"y":0.1431624},{"x":0.4318182,"y":0.14529915}]},"words":[{"property":{"detectedLanguages":[{"languageCode":"ta","confidence":1}]},"boundingBox":{"normalizedVertices":[{"x":0.4318182,"y":0.115384616},{"x":0.46969697,"y":0.115384616},{"x":0.46969697,"y":0.14529915},{"x":0.4318182,"y":0.14529915}]},"symbols":[{"property":{"detectedBreak":{"type":"SPACE"}},"text":"ஸ்ரீ","confidence":0.9823256}],"confidence":0.9823256},{"property":{"detectedLanguages":[{"languageCode":"ta","confidence":1}]},"boundingBox":{"normalizedVertices":[{"x":0.47474748,"y":0.115384616},{"x":0.57323235,"y":0.113247864},{"x":0.57323235,"y":0.1431624},{"x":0.47474748,"y":0.1431624}]},"symbols":[{"text":"ரா","confidence":0.96713704},{"text":"ம","confidence":0.97654754},{"text":"கீ","confidence":0.8485135},{"text":"தை","confidence":0.9721111}],"confidence":0.9410773},{"property":{"detectedLanguages":[{"languageCode":"ta","confidence":1}]},"boundingBox":{"normalizedVertices":[{"x":0.57575756,"y":0.113247864},{"x":0.57828283,"y":0.113247864},{"x":0.57828283,"y":0.1431624},{"x":0.57575756,"y":0.1431624}]},"symbols":[{"property":{"detectedBreak":{"type":"LINE_BREAK"}},"text":".","confidence":0.9607286}],"confidence":0.9607286}],"confidence":0.95122725}],"blockType":"TEXT","confidence":0.95122725},{"boundingBox":{"normalizedVertices":[{"x":0.8181818,"y":0.123931624},{"x":0.82323235,"y":0.123931624},{"x":0.82323235,"y":0.1388889},{"x":0.8181818,"y":0.1388889}]},"paragraphs":[{"boundingBox":{"normalizedVertices":[{"x":0.8181818,"y":0.123931624},{"x":0.82323235,"y":0.123931624},{"x":0.82323235,"y":0.1388889},{"x":0.8181818,"y":0.1388889}]},"words":[{"boundingBox":{"normalizedVertices":[{"x":0.8181818,"y":0.123931624},{"x":0.82323235,"y":0.123931624},{"x":0.82323235,"y":0.1388889},{"x":0.8181818,"y":0.1388889}]},"symbols":[{"property":{"detectedBreak":{"type":"LINE_BREAK"}},"text":"உ","confidence":0.74245554}],"confidence":0.74245554}],"confidence":0.74245554}],"blockType":"TEXT","confidence":0.74245554},{"boundingBox":{"normalizedVertices":[{"x":0.16666667,"y":0.16666667},{"x":0.8510101,"y":0.16666667},{"x":0.8484849,"y":0.73717946},{"x":0.16414142,"y":0.73504275}]},"paragraphs":[{"boundingBox":{"normalizedVertices":[{"x":0.17171717,"y":0.16666667},{"x":0.8510101,"y":0.16666667},{"x":0.8510101,"y":0.34188035},{"x":0.17171717,"y":0.34188035}]},"words":[{"property":{"detectedLanguages":[{"languageCode":"ta","confidence":1}]},"boundingBox":{"normalizedVertices":[{"x":0.17676768,"y":0.16666667},{"x":0.22474748,"y":0.16666667},{"x":0.22474748,"y":0.1923077},{"x":0.17676768,"y":0.1923077}]},"symbols":[{"text":"தி","confidence":0.957112},{"text":"ன்","confidence":0.9299902}],"confidence":0.94355106},{"property":{"detectedLanguages":[{"languageCode":"ta","confidence":1}]},"boundingBox":{"normalizedVertices":[{"x":0.22727273,"y":0.16666667},{"x":0.23484848,"y":0.16666667},{"x":0.23484848,"y":0.1923077},{"x":0.22727273,"y":0.1923077}]},"symbols":[{"property":{"detectedBreak":{"type":"SPACE"}},"text":")","confidence":0.9609764}],"confidence":0.9609764},{"property":{"detectedLanguages":[{"languageCode":"ta","confidence":1}]},"boundingBox":{"normalizedVertices":[{"x":0.24747474,"y":0.16666667},{"x":0.39141414,"y":0.16666667},{"x":0.39141414,"y":0.1923077},{"x":0.24747474,"y":0.1923077}]},"symbols":[{"text":"உ","confidence":0.99480844},{"text":"ற்ப","confidence":0.9952289},{"text":"த்தி","confidence":0.99649155},{"text":"யி","confidence":0.9983135},{"property":{"detectedBreak":{"type":"SPACE"}},"text":"ல்","confidence":0.9983712}],"confidence":0.9966427},{"property":{"detectedLanguages":[{"languageCode":"ta","confidence":1}]},"boundingBox":{"normalizedVertices":[{"x":0.41161618,"y":0.16666667},{"x":0.66161615,"y":0.16666667},{"x":0.66161615,"y":0.1923077},{"x":0.41161618,"y":0.1923077}]},"symbols":[{"text":"சி","confidence":0.9961705},{"text":"த்த","confidence":0.95537996},{"text":"சு","confidence":0.980343},{"text":"த்தி","confidence":0.9895318},{"text":"வா","confidence":0.97984135},{"text":"யி","confidence":0.9934179},{"text":"லா","confidence":0.9919311},{"text":"க","confidence":0.99648166},{"property":{"detectedBreak":{"type":"SPACE"}},"text":"க்","confidence":0.99363226}],"confidence":0.98630327},{"property":{"detectedLanguages":[{"languageCode":"ta","confidence":1}]},"boundingBox":{"normalizedVertices":[{"x":0.68686867,"y":0.16666667},{"x":0.8484849,"y":0.16666667},{"x":0.8484849,"y":0.1923077},{"x":0.68686867,"y":0.1923077}]},"symbols":[{"text":"க","confidence":0.9908848},{"text":"ர்மா","confidence":0.9125137},{"text":"பே","confidence":0.95171344},{"property":{"detectedBreak":{"type":"EOL_SURE_SPACE"}},"text":"க்ஷை","confidence":0.8766839}],"confidence":0.93294895},{"property":{"detectedLanguages":[{"languageCode":"ta","confidence":1}]},"boundingBox":{"normalizedVertices":[{"x":0.17676768,"y":0.19871795},{"x":0.22727273,"y":0.1965812},{"x":0.22727273,"y":0.21581197},{"x":0.17676768,"y":0.21581197}]},"symbols":[{"text":"யா","confidence":0.8700717},{"text":"ம்","confidence":0.9925632}],"confidence":0.93131745},{"property":{"detectedLanguages":[{"languageCode":"ta","confidence":1}]},"boundingBox":{"normalizedVertices":[{"x":0.22979797,"y":0.1965812},{"x":0.23484848,"y":0.1965812},{"x":0.23484848,"y":0.21367522},{"x":0.22979797,"y":0.21367522}]},"symbols":[{"property":{"detectedBreak":{"type":"SPACE"}},"text":".","confidence":0.93145066}],"confidence":0.93145066},{"property":{"detectedLanguages":[{"languageCode":"ta","confidence":1}]},"boundingBox":{"normalizedVertices":[{"x":0.26767677,"y":0.1965812},{"x":0.3409091,"y":0.1965812},{"x":0.3409091,"y":0.22435898},{"x":0.26767677,"y":0.22435898}]},"symbols":[{"text":"த","confidence":0.9913901},{"text":"ன","confidence":0.9974337},{"property":{"detectedBreak":{"type":"SPACE"}},"text":"து","confidence":0.99837345}],"confidence":0.9957324},{"property":{"detectedLanguages":[{"languageCode":"ta","confidence":1}]},"boundingBox":{"normalizedVertices":[{"x":0.3560606,"y":0.1965812},{"x":0.42676768,"y":0.1965812},{"x":0.42676768,"y":0.22435898},{"x":0.3560606,"y":0.22435898}]},"symbols":[{"text":"ப","confidence":0.9962656},{"text":"ய","confidence":0.9922983},{"property":{"detectedBreak":{"type":"SPACE"}},"text":"னை","confidence":0.96719307}],"confidence":0.9852523},{"property":{"detectedLanguages":[{"languageCode":"ta","confidence":1}]},"boundingBox":{"normalizedVertices":[{"x":0.42929292,"y":0.1965812},{"x":0.50757575,"y":0.1965812},{"x":0.50757575,"y":0.22435898},{"x":0.42929292,"y":0.22435898}]},"symbols":[{"text":"உ","confidence":0.9986971},{"property":{"detectedBreak":{"type":"SPACE"}},"text":"ண்டு","confidence":0.98840386}],"confidence":0.9935505},{"property":{"detectedLanguages":[{"languageCode":"ta","confidence":1}]},"boundingBox":{"normalizedVertices":[{"x":0.5050505,"y":0.1965812},{"x":0.7449495,"y":0.1965812},{"x":0.7449495,"y":0.22435898},{"x":0.5050505,"y":0.22435898}]},"symbols":[{"text":"ப","confidence":0.98040396},{"text":"ண்ணு","confidence":0.82643455},{"text":"ந்த","confidence":0.838268},{"text":"ன்மை","confidence":0.97455716},{"text":"யி","confidence":0.99755055},{"property":{"detectedBreak":{"type":"SPACE"}},"text":"ல்","confidence":0.99569434}],"confidence":0.93548477},{"property":{"detectedLanguages":[{"languageCode":"ta","confidence":1}]},"boundingBox":{"normalizedVertices":[{"x":0.77272725,"y":0.1965812},{"x":0.8510101,"y":0.1965812},{"x":0.8510101,"y":0.22435898},{"x":0.77272725,"y":0.22435898}]},"symbols":[{"text":"அ","confidence":0.996741},{"text":"க்க","confidence":0.99479026},{"property":{"detectedBreak":{"type":"EOL_SURE_SPACE"}},"text":"ர்","confidence":0.99171066}],"confidence":0.994414},{"property":{"detectedLanguages":[{"languageCode":"ta","confidence":1}]},"boundingBox":{"normalizedVertices":[{"x":0.17676768,"y":0.22435898},{"x":0.26262626,"y":0.22435898},{"x":0.26262626,"y":0.25213677},{"x":0.17676768,"y":0.25213677}]},"symbols":[{"text":"ம","confidence":0.9799228},{"text":"த்தி","confidence":0.979678},{"property":{"detectedBreak":{"type":"SPACE"}},"text":"ன்","confidence":0.9947961}],"confidence":0.98479897},{"property":{"detectedLanguages":[{"languageCode":"ta","confidence":1}]},"boundingBox":{"normalizedVertices":[{"x":0.28535354,"y":0.22435898},{"x":0.45454547,"y":0.22435898},{"x":0.45454547,"y":0.25213677},{"x":0.28535354,"y":0.25213677}]},"symbols":[{"text":"அ","confidence":0.9912093},{"text":"பே","confidence":0.9636667},{"text":"க்ஷை","confidence":0.9243213},{"text":"யி","confidence":0.98548603},{"property":{"detectedBreak":{"type":"SPACE"}},"text":"ன்","confidence":0.9661169}],"confidence":0.96616006},{"property":{"detectedLanguages":[{"languageCode":"ta","confidence":1}]},"boundingBox":{"normalizedVertices":[{"x":0.46212122,"y":0.22435898},{"x":0.59343433,"y":0.22435898},{"x":0.59343433,"y":0.25213677},{"x":0.46212122,"y":0.25213677}]},"symbols":[{"text":"றி","confidence":0.854028},{"text":"ய","confidence":0.969869},{"text":"தே","confidence":0.98262537},{"text":"யா","confidence":0.9933636},{"text":"ம்","confidence":0.99332035}],"confidence":0.9586413},{"property":{"detectedLanguages":[{"languageCode":"ta","confidence":1}]},"boundingBox":{"normalizedVertices":[{"x":0.5959596,"y":0.22435898},{"x":0.6010101,"y":0.22435898},{"x":0.6010101,"y":0.25213677},{"x":0.5959596,"y":0.25213677}]},"symbols":[{"property":{"detectedBreak":{"type":"SPACE"}},"text":".","confidence":0.9827368}],"confidence":0.9827368},{"property":{"detectedLanguages":[{"languageCode":"ta","confidence":1}]},"boundingBox":{"normalizedVertices":[{"x":0.64646465,"y":0.22435898},{"x":0.8459596,"y":0.22435898},{"x":0.8459596,"y":0.25213677},{"x":0.64646465,"y":0.25213677}]},"symbols":[{"text":"அ","confidence":0.99312925},{"text":"ப்ப","confidence":0.99276376},{"text":"டி","confidence":0.9939203},{"text":"க்கி","confidence":0.96464497},{"text":"ல்லை","confidence":0.97639644},{"property":{"detectedBreak":{"type":"EOL_SURE_SPACE"}},"text":"யா","confidence":0.9933283}],"confidence":0.98569715},{"property":{"detectedLanguages":[{"languageCode":"ta","confidence":1}]},"boundingBox":{"normalizedVertices":[{"x":0.17424242,"y":0.25641027},{"x":0.22474748,"y":0.25641027},{"x":0.22474748,"y":0.2820513},{"x":0.17424242,"y":0.2820513}]},"symbols":[{"text":"யி","confidence":0.96454763},{"text":"ன்","confidence":0.98693246}],"confidence":0.9757401},{"property":{"detectedLanguages":[{"languageCode":"ta","confidence":1}]},"boundingBox":{"normalizedVertices":[{"x":0.22727273,"y":0.25641027},{"x":0.23232323,"y":0.25641027},{"x":0.23232323,"y":0.2820513},{"x":0.22727273,"y":0.2820513}]},"symbols":[{"property":{"detectedBreak":{"type":"SPACE"}},"text":",","confidence":0.98522633}],"confidence":0.98522633},{"property":{"detectedLanguages":[{"languageCode":"ta","confidence":1}]},"boundingBox":{"normalizedVertices":[{"x":0.24494949,"y":0.25641027},{"x":0.38131315,"y":0.25641027},{"x":0.38131315,"y":0.2820513},{"x":0.24494949,"y":0.2820513}]},"symbols":[{"text":"வி","confidence":0.9914523},{"text":"த்தை","confidence":0.9679104},{"text":"யி","confidence":0.99513364},{"property":{"detectedBreak":{"type":"SPACE"}},"text":"ன்","confidence":0.99632317}],"confidence":0.9877049},{"property":{"detectedLanguages":[{"languageCode":"ta","confidence":1}]},"boundingBox":{"normalizedVertices":[{"x":0.3939394,"y":0.25641027},{"x":0.58838385,"y":0.25641027},{"x":0.58838385,"y":0.2820513},{"x":0.3939394,"y":0.2820513}]},"symbols":[{"text":"சொ","confidence":0.99135375},{"text":"ரூ","confidence":0.99751073},{"text":"ப","confidence":0.99840647},{"text":"த்தி","confidence":0.9898417},{"property":{"detectedBreak":{"type":"SPACE"}},"text":"ற்கே","confidence":0.97908723}],"confidence":0.99123996},{"property":{"detectedLanguages":[{"languageCode":"ta","confidence":1}]},"boundingBox":{"normalizedVertices":[{"x":0.6136364,"y":0.25641027},{"x":0.68686867,"y":0.25641027},{"x":0.68686867,"y":0.2820513},{"x":0.6136364,"y":0.2820513}]},"symbols":[{"text":"ப","confidence":0.99636054},{"text":"ங்க","confidence":0.99143994},{"property":{"detectedBreak":{"type":"SPACE"}},"text":"ம்","confidence":0.9960032}],"confidence":0.99460125},{"property":{"detectedLanguages":[{"languageCode":"ta","confidence":1}]},"boundingBox":{"normalizedVertices":[{"x":0.70454544,"y":0.25641027},{"x":0.8484849,"y":0.25641027},{"x":0.8484849,"y":0.2820513},{"x":0.70454544,"y":0.2820513}]},"symbols":[{"text":"வ","confidence":0.99688977},{"text":"ரு","confidence":0.9970221},{"text":"மா","confidence":0.9833735},{"text":"க","confidence":0.9917777},{"text":"லி","confidence":0.9896546},{"property":{"detectedBreak":{"type":"EOL_SURE_SPACE"}},"text":"ன்","confidence":0.9933155}],"confidence":0.9920055},{"property":{"detectedLanguages":[{"languageCode":"ta","confidence":1}]},"boundingBox":{"normalizedVertices":[{"x":0.17424242,"y":0.2863248},{"x":0.3131313,"y":0.2863248},{"x":0.3131313,"y":0.31196582},{"x":0.17424242,"y":0.31196582}]},"symbols":[{"text":"எ","confidence":0.99004734},{"text":"ன்ப","confidence":0.9942649},{"text":"த","confidence":0.9957655},{"text":"னா","confidence":0.97365785},{"property":{"detectedBreak":{"type":"SPACE"}},"text":"ல்","confidence":0.9909369}],"confidence":0.9889345},{"property":{"detectedLanguages":[{"languageCode":"ta","confidence":1}]},"boundingBox":{"normalizedVertices":[{"x":0.32323232,"y":0.2863248},{"x":0.4368687,"y":0.2863248},{"x":0.4368687,"y":0.31196582},{"x":0.32323232,"y":0.31196582}]},"symbols":[{"text":"பூ","confidence":0.9962311},{"text":"ர்வ","confidence":0.9854683},{"text":"ப","confidence":0.9920544},{"property":{"detectedBreak":{"type":"SPACE"}},"text":"க்ஷி","confidence":0.9376672}],"confidence":0.97785527},{"property":{"detectedLanguages":[{"languageCode":"ta","confidence":1}]},"boundingBox":{"normalizedVertices":[{"x":0.4520202,"y":0.2863248},{"x":0.52020204,"y":0.2863248},{"x":0.52020204,"y":0.31196582},{"x":0.4520202,"y":0.31196582}]},"symbols":[{"text":"கூ","confidence":0.9779838},{"text":"றி","confidence":0.9900856},{"property":{"detectedBreak":{"type":"SPACE"}},"text":"ய","confidence":0.98826784}],"confidence":0.98544574},{"property":{"detectedLanguages":[{"languageCode":"ta","confidence":1}]},"boundingBox":{"normalizedVertices":[{"x":0.540404,"y":0.2863248},{"x":0.59090906,"y":0.2863248},{"x":0.59090906,"y":0.31196582},{"x":0.540404,"y":0.31196582}]},"symbols":[{"text":"ஏ","confidence":0.9190772},{"property":{"detectedBreak":{"type":"SPACE"}},"text":"து","confidence":0.96549934}],"confidence":0.9422883},{"property":{"detectedLanguages":[{"languageCode":"ta","confidence":1}]},"boundingBox":{"normalizedVertices":[{"x":0.6136364,"y":0.2863248},{"x":0.7777778,"y":0.2863248},{"x":0.7777778,"y":0.31196582},{"x":0.6136364,"y":0.31196582}]},"symbols":[{"text":"சி","confidence":0.9932061},{"text":"த்தி","confidence":0.99459386},{"text":"யா","confidence":0.9906186},{"text":"த","confidence":0.99029475},{"text":"தா","confidence":0.97802716},{"property":{"detectedBreak":{"type":"SPACE"}},"text":"ம்","confidence":0.9885401}],"confidence":0.9892134},{"property":{"detectedLanguages":[{"languageCode":"ta","confidence":1}]},"boundingBox":{"normalizedVertices":[{"x":0.80050504,"y":0.2863248},{"x":0.8459596,"y":0.2863248},{"x":0.8459596,"y":0.31196582},{"x":0.80050504,"y":0.31196582}]},"symbols":[{"text":"எ","confidence":0.991672},{"property":{"detectedBreak":{"type":"EOL_SURE_SPACE"}},"text":"ன்","confidence":0.99259675}],"confidence":0.99213433},{"property":{"detectedLanguages":[{"languageCode":"ta","confidence":1}]},"boundingBox":{"normalizedVertices":[{"x":0.17171717,"y":0.31623933},{"x":0.21717171,"y":0.31623933},{"x":0.21717171,"y":0.33974358},{"x":0.17171717,"y":0.33974358}]},"symbols":[{"text":"ப","confidence":0.97068703},{"property":{"detectedBreak":{"type":"SPACE"}},"text":"து","confidence":0.9881392}],"confidence":0.97941315},{"property":{"detectedLanguages":[{"languageCode":"ta","confidence":1}]},"boundingBox":{"normalizedVertices":[{"x":0.22979797,"y":0.31623933},{"x":0.3131313,"y":0.31623933},{"x":0.3131313,"y":0.33974358},{"x":0.22979797,"y":0.33974358}]},"symbols":[{"text":"க","confidence":0.9899858},{"text":"ரு","confidence":0.99107814},{"text":"த்து","confidence":0.98294765}],"confidence":0.98800385},{"property":{"detectedLanguages":[{"languageCode":"ta","confidence":1}]},"boundingBox":{"normalizedVertices":[{"x":0.3181818,"y":0.31623933},{"x":0.32828283,"y":0.31623933},{"x":0.32828283,"y":0.33974358},{"x":0.3181818,"y":0.33974358}]},"symbols":[{"property":{"detectedBreak":{"type":"EOL_SURE_SPACE"}},"text":".","confidence":0.9275955}],"confidence":0.9275955},{"property":{"detectedLanguages":[{"languageCode":"ta","confidence":1}]},"boundingBox":{"normalizedVertices":[{"x":0.7878788,"y":0.31623933},{"x":0.7979798,"y":0.31623933},{"x":0.7979798,"y":0.34188035},{"x":0.7878788,"y":0.34188035}]},"symbols":[{"text":"(","confidence":0.96907306}],"confidence":0.96907306},{"property":{"detectedLanguages":[{"languageCode":"ta","confidence":1}]},"boundingBox":{"normalizedVertices":[{"x":0.80050504,"y":0.31410256},{"x":0.8358586,"y":0.31623933},{"x":0.8358586,"y":0.34188035},{"x":0.80050504,"y":0.34188035}]},"symbols":[{"text":"க","confidence":0.98591995},{"text":"ரு","confidence":0.98093164}],"confidence":0.9834258},{"property":{"detectedLanguages":[{"languageCode":"ta","confidence":1}]},"boundingBox":{"normalizedVertices":[{"x":0.83838385,"y":0.31623933},{"x":0.8484849,"y":0.31623933},{"x":0.8484849,"y":0.34188035},{"x":0.83838385,"y":0.34188035}]},"symbols":[{"property":{"detectedBreak":{"type":"LINE_BREAK"}},"text":")","confidence":0.97039604}],"confidence":0.97039604}],"confidence":0.9770904},{"boundingBox":{"normalizedVertices":[{"x":0.16666667,"y":0.36752138},{"x":0.8080808,"y":0.37179488},{"x":0.8055556,"y":0.44658118},{"x":0.16666667,"y":0.44230768}]},"words":[{"property":{"detectedLanguages":[{"languageCode":"sa","confidence":1}]},"boundingBox":{"normalizedVertices":[{"x":0.16919191,"y":0.36752138},{"x":0.40656567,"y":0.3696581},{"x":0.40656567,"y":0.4017094},{"x":0.16919191,"y":0.39957264}]},"symbols":[{"text":"त","confidence":0.9446397},{"text":"स्मा","confidence":0.8363833},{"text":"त्त्य","confidence":0.80158335},{"text":"जे","confidence":0.91532546},{"text":"त्का","confidence":0.8734662},{"text":"र्य","confidence":0.9599795},{"text":"म","confidence":0.97310644},{"text":"शे","confidence":0.9560848},{"text":"ष","confidence":0.95340395},{"property":{"detectedBreak":{"type":"SPACE"}},"text":"तः","confidence":0.86678684}],"confidence":0.9080759},{"property":{"detectedLanguages":[{"languageCode":"sa","confidence":1}]},"boundingBox":{"normalizedVertices":[{"x":0.41666666,"y":0.3696581},{"x":0.5984849,"y":0.3696581},{"x":0.5984849,"y":0.4017094},{"x":0.41666666,"y":0.4017094}]},"symbols":[{"text":"सु","confidence":0.9400027},{"text":"धी","confidence":0.915807},{"text":"र्वि","confidence":0.8489595},{"text":"द्या","confidence":0.90142566},{"text":"वि","confidence":0.9492842},{"text":"रो","confidence":0.96089035},{"text":"धा","confidence":0.92391706},{"property":{"detectedBreak":{"type":"SPACE"}},"text":"न्न","confidence":0.7783364}],"confidence":0.90232784},{"property":{"detectedLanguages":[{"languageCode":"sa","confidence":1}]},"boundingBox":{"normalizedVertices":[{"x":0.60858583,"y":0.3696581},{"x":0.6919192,"y":0.37179488},{"x":0.6919192,"y":0.40384614},{"x":0.60858583,"y":0.4017094}]},"symbols":[{"text":"स","confidence":0.9603772},{"text":"मु","confidence":0.9268253},{"text":"च्च","confidence":0.8230947},{"property":{"detectedBreak":{"type":"SPACE"}},"text":"यो","confidence":0.91508025}],"confidence":0.90634435},{"property":{"detectedLanguages":[{"languageCode":"sa","confidence":1}]},"boundingBox":{"normalizedVertices":[{"x":0.709596,"y":0.37179488},{"x":0.760101,"y":0.37179488},{"x":0.760101,"y":0.40384614},{"x":0.709596,"y":0.40384614}]},"symbols":[{"text":"भ","confidence":0.97206986},{"text":"वे","confidence":0.9225895},{"property":{"detectedBreak":{"type":"SPACE"}},"text":"त्","confidence":0.912656}],"confidence":0.93577176},{"property":{"detectedLanguages":[{"languageCode":"sa","confidence":1}]},"boundingBox":{"normalizedVertices":[{"x":0.77272725,"y":0.37179488},{"x":0.7777778,"y":0.37179488},{"x":0.7777778,"y":0.40384614},{"x":0.77272725,"y":0.40384614}]},"symbols":[{"property":{"detectedBreak":{"type":"EOL_SURE_SPACE"}},"text":"!","confidence":0.72477394}],"confidence":0.72477394},{"property":{"detectedLanguages":[{"languageCode":"sa","confidence":1}]},"boundingBox":{"normalizedVertices":[{"x":0.16666667,"y":0.41025642},{"x":0.39141414,"y":0.41239315},{"x":0.39141414,"y":0.44444445},{"x":0.16666667,"y":0.44230768}]},"symbols":[{"text":"आ","confidence":0.9760549},{"text":"त्मा","confidence":0.91167486},{"text":"नु","confidence":0.9522637},{"text":"सं","confidence":0.95099545},{"text":"धा","confidence":0.8825555},{"text":"न","confidence":0.9745761},{"text":"प","confidence":0.9705631},{"text":"रा","confidence":0.96362525},{"text":"य","confidence":0.9646048},{"property":{"detectedBreak":{"type":"SPACE"}},"text":"णः","confidence":0.8060854}],"confidence":0.93529993},{"property":{"detectedLanguages":[{"languageCode":"sa","confidence":1}]},"boundingBox":{"normalizedVertices":[{"x":0.40151516,"y":0.41239315},{"x":0.44949496,"y":0.41239315},{"x":0.44949496,"y":0.44444445},{"x":0.40151516,"y":0.44444445}]},"symbols":[{"text":"स","confidence":0.97993475},{"property":{"detectedBreak":{"type":"SPACE"}},"text":"दा","confidence":0.95331633}],"confidence":0.9666256},{"property":{"detectedLanguages":[{"languageCode":"sa","confidence":1}]},"boundingBox":{"normalizedVertices":[{"x":0.4570707,"y":0.41239315},{"x":0.5176768,"y":0.41239315},{"x":0.5176768,"y":0.44444445},{"x":0.4570707,"y":0.44444445}]},"symbols":[{"text":"नि","confidence":0.9495419},{"text":"वृ","confidence":0.9683818},{"property":{"detectedBreak":{"type":"SPACE"}},"text":"त्त","confidence":0.93800294}],"confidence":0.9519756},{"property":{"detectedLanguages":[{"languageCode":"sa","confidence":1}]},"boundingBox":{"normalizedVertices":[{"x":0.5176768,"y":0.41239315},{"x":0.709596,"y":0.41239315},{"x":0.709596,"y":0.44658118},{"x":0.5176768,"y":0.44444445}]},"symbols":[{"text":"स","confidence":0.9597702},{"text":"र्वे","confidence":0.86807734},{"text":"न्द्रि","confidence":0.77703345},{"text":"य","confidence":0.9650317},{"text":"वृ","confidence":0.95051944},{"text":"त्ति","confidence":0.9218369},{"text":"गो","confidence":0.9407325},{"text":"च","confidence":0.97605926},{"property":{"detectedBreak":{"type":"SPACE"}},"text":"रः","confidence":0.8946762}],"confidence":0.9170819},{"property":{"detectedLanguages":[{"languageCode":"sa","confidence":1}]},"boundingBox":{"normalizedVertices":[{"x":0.7222222,"y":0.41239315},{"x":0.72727275,"y":0.41239315},{"x":0.72727275,"y":0.44444445},{"x":0.7222222,"y":0.44444445}]},"symbols":[{"property":{"detectedBreak":{"type":"SPACE"}},"text":"॥","confidence":0.94129235}],"confidence":0.94129235},{"property":{"detectedLanguages":[{"languageCode":"sa","confidence":1}]},"boundingBox":{"normalizedVertices":[{"x":0.75757575,"y":0.41239315},{"x":0.7878788,"y":0.41239315},{"x":0.7878788,"y":0.44658118},{"x":0.75757575,"y":0.44658118}]},"symbols":[{"text":"१","confidence":0.9319596},{"property":{"detectedBreak":{"type":"SPACE"}},"text":"६","confidence":0.9410071}],"confidence":0.9364834},{"property":{"detectedLanguages":[{"languageCode":"sa","confidence":1}]},"boundingBox":{"normalizedVertices":[{"x":0.7979798,"y":0.41239315},{"x":0.8080808,"y":0.41239315},{"x":0.8080808,"y":0.44658118},{"x":0.7979798,"y":0.44658118}]},"symbols":[{"property":{"detectedBreak":{"type":"LINE_BREAK"}},"text":"॥","confidence":0.95122546}],"confidence":0.95122546}],"confidence":0.91885644},{"boundingBox":{"normalizedVertices":[{"x":0.17424242,"y":0.4636752},{"x":0.84343433,"y":0.46581197},{"x":0.84343433,"y":0.52350426},{"x":0.17424242,"y":0.52136755}]},"words":[{"property":{"detectedLanguages":[{"languageCode":"ta","confidence":1}]},"boundingBox":{"normalizedVertices":[{"x":0.23737374,"y":0.4636752},{"x":0.25,"y":0.4636752},{"x":0.25,"y":0.491453},{"x":0.23737374,"y":0.491453}]},"symbols":[{"text":"(","confidence":0.91688657}],"confidence":0.91688657},{"property":{"detectedLanguages":[{"languageCode":"ta","confidence":1}]},"boundingBox":{"normalizedVertices":[{"x":0.2550505,"y":0.4636752},{"x":0.26767677,"y":0.4636752},{"x":0.26767677,"y":0.491453},{"x":0.2550505,"y":0.491453}]},"symbols":[{"text":"அ","confidence":0.9430188}],"confidence":0.9430188},{"property":{"detectedLanguages":[{"languageCode":"ta","confidence":1}]},"boundingBox":{"normalizedVertices":[{"x":0.270202,"y":0.4636752},{"x":0.28535354,"y":0.4636752},{"x":0.28535354,"y":0.491453},{"x":0.270202,"y":0.491453}]},"symbols":[{"text":"-","confidence":0.9733111}],"confidence":0.9733111},{"property":{"detectedLanguages":[{"languageCode":"ta","confidence":1}]},"boundingBox":{"normalizedVertices":[{"x":0.2929293,"y":0.4636752},{"x":0.32575756,"y":0.4636752},{"x":0.32575756,"y":0.491453},{"x":0.2929293,"y":0.491453}]},"symbols":[{"text":"கை","confidence":0.9647992}],"confidence":0.9647992},{"property":{"detectedLanguages":[{"languageCode":"ta","confidence":1}]},"boundingBox":{"normalizedVertices":[{"x":0.32575756,"y":0.4636752},{"x":0.33333334,"y":0.4636752},{"x":0.33333334,"y":0.491453},{"x":0.32575756,"y":0.491453}]},"symbols":[{"text":".","confidence":0.857276}],"confidence":0.857276},{"property":{"detectedLanguages":[{"languageCode":"ta","confidence":1}]},"boundingBox":{"normalizedVertices":[{"x":0.33585858,"y":0.4636752},{"x":0.3459596,"y":0.4636752},{"x":0.3459596,"y":0.491453},{"x":0.33585858,"y":0.491453}]},"symbols":[{"property":{"detectedBreak":{"type":"SPACE"}},"text":")","confidence":0.9539767}],"confidence":0.9539767},{"property":{"detectedLanguages":[{"languageCode":"ta","confidence":1}]},"boundingBox":{"normalizedVertices":[{"x":0.3611111,"y":0.4636752},{"x":0.530303,"y":0.46581197},{"x":0.530303,"y":0.491453},{"x":0.3611111,"y":0.491453}]},"symbols":[{"text":"மு","confidence":0.97813475},{"text":"ற்கூ","confidence":0.9746897},{"text":"றி","confidence":0.98961383},{"text":"ய","confidence":0.99315965},{"text":"த","confidence":0.99077606},{"property":{"detectedBreak":{"type":"SPACE"}},"text":"னை","confidence":0.9902584}],"confidence":0.9861054},{"property":{"detectedLanguages":[{"languageCode":"ta","confidence":1}]},"boundingBox":{"normalizedVertices":[{"x":0.540404,"y":0.46581197},{"x":0.6363636,"y":0.46581197},{"x":0.6363636,"y":0.491453},{"x":0.540404,"y":0.491453}]},"symbols":[{"text":"மு","confidence":0.9939634},{"text":"டி","confidence":0.99525845},{"property":{"detectedBreak":{"type":"SPACE"}},"text":"த்து","confidence":0.9952456}],"confidence":0.9948225},{"property":{"detectedLanguages":[{"languageCode":"ta","confidence":1}]},"boundingBox":{"normalizedVertices":[{"x":0.6489899,"y":0.46581197},{"x":0.84343433,"y":0.46581197},{"x":0.84343433,"y":0.49358973},{"x":0.6489899,"y":0.491453}]},"symbols":[{"text":"மு","confidence":0.91783035},{"text":"மு","confidence":0.8336551},{"text":"க்ஷ","confidence":0.89629936},{"text":"வி","confidence":0.9128107},{"text":"ன","confidence":0.9862036},{"property":{"detectedBreak":{"type":"EOL_SURE_SPACE"}},"text":"து","confidence":0.9818602}],"confidence":0.9214432},{"property":{"detectedLanguages":[{"languageCode":"ta","confidence":1}]},"boundingBox":{"normalizedVertices":[{"x":0.17424242,"y":0.4957265},{"x":0.48232323,"y":0.4957265},{"x":0.48232323,"y":0.52136755},{"x":0.17424242,"y":0.52136755}]},"symbols":[{"text":"வி","confidence":0.9735775},{"text":"ரு","confidence":0.98964703},{"text":"த்தி","confidence":0.9696299},{"text":"யி","confidence":0.98886055},{"text":"ன்ற","confidence":0.98172456},{"text":"ன்மை","confidence":0.96396005},{"text":"யி","confidence":0.98923826},{"text":"னை","confidence":0.99027765},{"property":{"detectedBreak":{"type":"SPACE"}},"text":"க்","confidence":0.9967699}],"confidence":0.9826317},{"property":{"detectedLanguages":[{"languageCode":"ta","confidence":1}]},"boundingBox":{"normalizedVertices":[{"x":0.49242425,"y":0.4957265},{"x":0.63131315,"y":0.4957265},{"x":0.63131315,"y":0.52136755},{"x":0.49242425,"y":0.52136755}]},"symbols":[{"text":"கூ","confidence":0.9974202},{"text":"று","confidence":0.9987794},{"text":"கி","confidence":0.996294},{"text":"ன்றா","confidence":0.9730606},{"text":"ர்","confidence":0.97028005}],"confidence":0.9871669},{"property":{"detectedLanguages":[{"languageCode":"ta","confidence":1}]},"boundingBox":{"normalizedVertices":[{"x":0.6363636,"y":0.4957265},{"x":0.6489899,"y":0.4957265},{"x":0.6489899,"y":0.52136755},{"x":0.6363636,"y":0.52136755}]},"symbols":[{"text":":","confidence":0.86856854}],"confidence":0.86856854},{"property":{"detectedLanguages":[{"languageCode":"ta","confidence":1}]},"boundingBox":{"normalizedVertices":[{"x":0.65656567,"y":0.4957265},{"x":0.6792929,"y":0.4957265},{"x":0.6792929,"y":0.52136755},{"x":0.65656567,"y":0.52136755}]},"symbols":[{"property":{"detectedBreak":{"type":"LINE_BREAK"}},"text":"-","confidence":0.76413757}],"confidence":0.76413757}],"confidence":0.958142},{"boundingBox":{"normalizedVertices":[{"x":0.17171717,"y":0.53205127},{"x":0.8484849,"y":0.53418803},{"x":0.8484849,"y":0.60470086},{"x":0.16919191,"y":0.6025641}]},"words":[{"property":{"detectedLanguages":[{"languageCode":"sa","confidence":1}]},"boundingBox":{"normalizedVertices":[{"x":0.20959596,"y":0.53418803},{"x":0.35353535,"y":0.53418803},{"x":0.35353535,"y":0.5641026},{"x":0.20959596,"y":0.5641026}]},"symbols":[{"text":"वि","confidence":0.8819683},{"text":"द्या","confidence":0.9272472},{"text":"वि","confidence":0.9563252},{"text":"रो","confidence":0.9515534},{"text":"धा","confidence":0.82398957},{"property":{"detectedBreak":{"type":"SPACE"}},"text":"त्","confidence":0.9501681}],"confidence":0.91520864},{"property":{"detectedLanguages":[{"languageCode":"sa","confidence":1}]},"boundingBox":{"normalizedVertices":[{"x":0.37121212,"y":0.53418803},{"x":0.45959595,"y":0.53418803},{"x":0.45959595,"y":0.5641026},{"x":0.37121212,"y":0.5641026}]},"symbols":[{"text":"स","confidence":0.9638885},{"text":"मु","confidence":0.93325514},{"text":"च्च","confidence":0.7781481},{"property":{"detectedBreak":{"type":"SPACE"}},"text":"यः","confidence":0.83850527}],"confidence":0.87844926},{"property":{"detectedLanguages":[{"languageCode":"sa","confidence":1}]},"boundingBox":{"normalizedVertices":[{"x":0.46969697,"y":0.53418803},{"x":0.49242425,"y":0.53418803},{"x":0.49242425,"y":0.5641026},{"x":0.46969697,"y":0.5641026}]},"symbols":[{"property":{"detectedBreak":{"type":"SPACE"}},"text":"न","confidence":0.9758734}],"confidence":0.9758734},{"property":{"detectedLanguages":[{"languageCode":"sa","confidence":1}]},"boundingBox":{"normalizedVertices":[{"x":0.5126263,"y":0.53418803},{"x":0.57323235,"y":0.53418803},{"x":0.57323235,"y":0.5641026},{"x":0.5126263,"y":0.5641026}]},"symbols":[{"text":"भ","confidence":0.9889403},{"text":"वे","confidence":0.9815148},{"property":{"detectedBreak":{"type":"SPACE"}},"text":"त्","confidence":0.9866199}],"confidence":0.98569167},{"property":{"detectedLanguages":[{"languageCode":"sa","confidence":1}]},"boundingBox":{"normalizedVertices":[{"x":0.58838385,"y":0.53418803},{"x":0.6666667,"y":0.53418803},{"x":0.6666667,"y":0.5641026},{"x":0.58838385,"y":0.5641026}]},"symbols":[{"text":"त","confidence":0.9761007},{"text":"स्मा","confidence":0.9240857},{"property":{"detectedBreak":{"type":"SPACE"}},"text":"त्","confidence":0.97843945}],"confidence":0.9595419},{"property":{"detectedLanguages":[{"languageCode":"sa","confidence":1}]},"boundingBox":{"normalizedVertices":[{"x":0.68434346,"y":0.53418803},{"x":0.74242425,"y":0.53418803},{"x":0.74242425,"y":0.5641026},{"x":0.68434346,"y":0.5641026}]},"symbols":[{"text":"सु","confidence":0.9625729},{"property":{"detectedBreak":{"type":"SPACE"}},"text":"धीः","confidence":0.7449822}],"confidence":0.8537775},{"property":{"detectedLanguages":[{"languageCode":"sa","confidence":1}]},"boundingBox":{"normalizedVertices":[{"x":0.7626263,"y":0.53418803},{"x":0.8484849,"y":0.53418803},{"x":0.8484849,"y":0.5641026},{"x":0.7626263,"y":0.5641026}]},"symbols":[{"text":"अ","confidence":0.95960325},{"text":"शे","confidence":0.94348204},{"text":"ष","confidence":0.9774117},{"property":{"detectedBreak":{"type":"EOL_SURE_SPACE"}},"text":"तः","confidence":0.947402}],"confidence":0.95697474},{"property":{"detectedLanguages":[{"languageCode":"sa","confidence":1}]},"boundingBox":{"normalizedVertices":[{"x":0.17171717,"y":0.5726496},{"x":0.23737374,"y":0.5726496},{"x":0.23484848,"y":0.6025641},{"x":0.16919191,"y":0.6025641}]},"symbols":[{"text":"का","confidence":0.95826834},{"text":"र्य","confidence":0.9592465},{"property":{"detectedBreak":{"type":"SPACE"}},"text":"म्","confidence":0.92922795}],"confidence":0.9489143},{"property":{"detectedLanguages":[{"languageCode":"sa","confidence":1}]},"boundingBox":{"normalizedVertices":[{"x":0.25,"y":0.5726496},{"x":0.31060606,"y":0.5726496},{"x":0.30808082,"y":0.6025641},{"x":0.24747474,"y":0.6025641}]},"symbols":[{"text":"त्य","confidence":0.91457117},{"text":"जे","confidence":0.9428277},{"property":{"detectedBreak":{"type":"SPACE"}},"text":"त्","confidence":0.9436548}],"confidence":0.9336845},{"property":{"detectedLanguages":[{"languageCode":"sa","confidence":1}]},"boundingBox":{"normalizedVertices":[{"x":0.32323232,"y":0.5726496},{"x":0.32828283,"y":0.5726496},{"x":0.32828283,"y":0.6025641},{"x":0.32323232,"y":0.6025641}]},"symbols":[{"property":{"detectedBreak":{"type":"LINE_BREAK"}},"text":"॥","confidence":0.8648514}],"confidence":0.8648514}],"confidence":0.9288242},{"boundingBox":{"normalizedVertices":[{"x":0.17171717,"y":0.6217949},{"x":0.8459596,"y":0.6217949},{"x":0.8459596,"y":0.73504275},{"x":0.17171717,"y":0.73504275}]},"words":[{"property":{"detectedLanguages":[{"languageCode":"ta","confidence":1}]},"boundingBox":{"normalizedVertices":[{"x":0.23232323,"y":0.6217949},{"x":0.24494949,"y":0.6217949},{"x":0.24494949,"y":0.6474359},{"x":0.23232323,"y":0.6474359}]},"symbols":[{"text":"(","confidence":0.88470787}],"confidence":0.88470787},{"property":{"detectedLanguages":[{"languageCode":"ta","confidence":1}]},"boundingBox":{"normalizedVertices":[{"x":0.25252524,"y":0.6217949},{"x":0.2651515,"y":0.6217949},{"x":0.2651515,"y":0.6474359},{"x":0.25252524,"y":0.6474359}]},"symbols":[{"text":"இ","confidence":0.9467548}],"confidence":0.9467548},{"property":{"detectedLanguages":[{"languageCode":"ta","confidence":1}]},"boundingBox":{"normalizedVertices":[{"x":0.2651515,"y":0.6217949},{"x":0.2777778,"y":0.6217949},{"x":0.2777778,"y":0.6474359},{"x":0.2651515,"y":0.6474359}]},"symbols":[{"text":"-","confidence":0.9612832}],"confidence":0.9612832},{"property":{"detectedLanguages":[{"languageCode":"ta","confidence":1}]},"boundingBox":{"normalizedVertices":[{"x":0.28535354,"y":0.6217949},{"x":0.30050504,"y":0.6217949},{"x":0.30050504,"y":0.6474359},{"x":0.28535354,"y":0.6474359}]},"symbols":[{"text":"ள்","confidence":0.9853009}],"confidence":0.9853009},{"property":{"detectedLanguages":[{"languageCode":"ta","confidence":1}]},"boundingBox":{"normalizedVertices":[{"x":0.30808082,"y":0.6217949},{"x":0.32070708,"y":0.6217949},{"x":0.32070708,"y":0.6474359},{"x":0.30808082,"y":0.6474359}]},"symbols":[{"property":{"detectedBreak":{"type":"SPACE"}},"text":")","confidence":0.9895147}],"confidence":0.9895147},{"property":{"detectedLanguages":[{"languageCode":"ta","confidence":1}]},"boundingBox":{"normalizedVertices":[{"x":0.35353535,"y":0.6217949},{"x":0.4848485,"y":0.6217949},{"x":0.4848485,"y":0.6474359},{"x":0.35353535,"y":0.6474359}]},"symbols":[{"text":"வி","confidence":0.99454963},{"text":"த்தை","confidence":0.9874049},{"property":{"detectedBreak":{"type":"SPACE"}},"text":"க்கு","confidence":0.9905291}],"confidence":0.99082786},{"property":{"detectedLanguages":[{"languageCode":"ta","confidence":1}]},"boundingBox":{"normalizedVertices":[{"x":0.49242425,"y":0.6217949},{"x":0.5,"y":0.6217949},{"x":0.5,"y":0.6474359},{"x":0.49242425,"y":0.6474359}]},"symbols":[{"text":"(","confidence":0.9873799}],"confidence":0.9873799},{"property":{"detectedLanguages":[{"languageCode":"ta","confidence":1}]},"boundingBox":{"normalizedVertices":[{"x":0.50252527,"y":0.6217949},{"x":0.64141417,"y":0.6217949},{"x":0.64141417,"y":0.6474359},{"x":0.50252527,"y":0.6474359}]},"symbols":[{"text":"க","confidence":0.99113655},{"text":"ர்ம","confidence":0.98480636},{"text":"த்தோ","confidence":0.97439086},{"text":"டு","confidence":0.98905843}],"confidence":0.984848},{"property":{"detectedLanguages":[{"languageCode":"ta","confidence":1}]},"boundingBox":{"normalizedVertices":[{"x":0.64646465,"y":0.6217949},{"x":0.65656567,"y":0.6217949},{"x":0.65656567,"y":0.6474359},{"x":0.64646465,"y":0.6474359}]},"symbols":[{"property":{"detectedBreak":{"type":"SPACE"}},"text":")","confidence":0.96904653}],"confidence":0.96904653},{"property":{"detectedLanguages":[{"languageCode":"ta","confidence":1}]},"boundingBox":{"normalizedVertices":[{"x":0.6666667,"y":0.6217949},{"x":0.7550505,"y":0.6217949},{"x":0.7550505,"y":0.6474359},{"x":0.6666667,"y":0.6474359}]},"symbols":[{"text":"வி","confidence":0.98205745},{"text":"ரோ","confidence":0.9647461},{"property":{"detectedBreak":{"type":"SPACE"}},"text":"த","confidence":0.9954796}],"confidence":0.98076105},{"property":{"detectedLanguages":[{"languageCode":"ta","confidence":1}]},"boundingBox":{"normalizedVertices":[{"x":0.7777778,"y":0.6217949},{"x":0.84343433,"y":0.6217949},{"x":0.84343433,"y":0.6474359},{"x":0.7777778,"y":0.6474359}]},"symbols":[{"text":"மி","confidence":0.99294585},{"text":"ரு","confidence":0.98994356},{"property":{"detectedBreak":{"type":"EOL_SURE_SPACE"}},"text":"த்","confidence":0.9534937}],"confidence":0.9787944},{"property":{"detectedLanguages":[{"languageCode":"ta","confidence":1}]},"boundingBox":{"normalizedVertices":[{"x":0.17171717,"y":0.6474359},{"x":0.24494949,"y":0.6474359},{"x":0.24494949,"y":0.6752137},{"x":0.17171717,"y":0.6752137}]},"symbols":[{"text":"த","confidence":0.9860527},{"text":"லா","confidence":0.98817766},{"property":{"detectedBreak":{"type":"SPACE"}},"text":"ல்","confidence":0.9937773}],"confidence":0.9893359},{"property":{"detectedLanguages":[{"languageCode":"ta","confidence":1}]},"boundingBox":{"normalizedVertices":[{"x":0.2651515,"y":0.6474359},{"x":0.3661616,"y":0.6474359},{"x":0.3661616,"y":0.6752137},{"x":0.2651515,"y":0.6752137}]},"symbols":[{"text":"ச","confidence":0.9451325},{"text":"மு","confidence":0.75867456},{"text":"ச்ச","confidence":0.93109983},{"property":{"detectedBreak":{"type":"SPACE"}},"text":"ய","confidence":0.9904826}],"confidence":0.9063474},{"property":{"detectedLanguages":[{"languageCode":"ta","confidence":1}]},"boundingBox":{"normalizedVertices":[{"x":0.37626263,"y":0.6474359},{"x":0.52272725,"y":0.6474359},{"x":0.52272725,"y":0.6752137},{"x":0.37626263,"y":0.6752137}]},"symbols":[{"text":"மு","confidence":0.9808861},{"text":"ண்டா","confidence":0.9445554},{"text":"கா","confidence":0.9909675},{"text":"து","confidence":0.99348146}],"confidence":0.9774726},{"property":{"detectedLanguages":[{"languageCode":"ta","confidence":1}]},"boundingBox":{"normalizedVertices":[{"x":0.5277778,"y":0.6474359},{"x":0.5378788,"y":0.6474359},{"x":0.5378788,"y":0.6752137},{"x":0.5277778,"y":0.6752137}]},"symbols":[{"property":{"detectedBreak":{"type":"SPACE"}},"text":".","confidence":0.9773195}],"confidence":0.9773195},{"property":{"detectedLanguages":[{"languageCode":"ta","confidence":1}]},"boundingBox":{"normalizedVertices":[{"x":0.5707071,"y":0.6474359},{"x":0.6666667,"y":0.6474359},{"x":0.6666667,"y":0.6752137},{"x":0.5707071,"y":0.6752137}]},"symbols":[{"text":"ஆ","confidence":0.99283266},{"text":"த","confidence":0.99481076},{"text":"லா","confidence":0.9936517},{"property":{"detectedBreak":{"type":"SPACE"}},"text":"ல்","confidence":0.99751246}],"confidence":0.99470186},{"property":{"detectedLanguages":[{"languageCode":"ta","confidence":1}]},"boundingBox":{"normalizedVertices":[{"x":0.6818182,"y":0.6474359},{"x":0.84343433,"y":0.6474359},{"x":0.84343433,"y":0.6752137},{"x":0.6818182,"y":0.6752137}]},"symbols":[{"text":"ந","confidence":0.9836677},{"text":"ற்பு","confidence":0.9867964},{"text":"த்தி","confidence":0.9934013},{"text":"யு","confidence":0.9944271},{"property":{"detectedBreak":{"type":"EOL_SURE_SPACE"}},"text":"டை","confidence":0.9891118}],"confidence":0.98948085},{"property":{"detectedLanguages":[{"languageCode":"ta","confidence":1}]},"boundingBox":{"normalizedVertices":[{"x":0.17171717,"y":0.6773504},{"x":0.24494949,"y":0.6773504},{"x":0.24494949,"y":0.70726496},{"x":0.17171717,"y":0.70726496}]},"symbols":[{"text":"யோ","confidence":0.9713984},{"property":{"detectedBreak":{"type":"SPACE"}},"text":"ன்","confidence":0.9500344}],"confidence":0.96071637},{"property":{"detectedLanguages":[{"languageCode":"ta","confidence":1}]},"boundingBox":{"normalizedVertices":[{"x":0.24242425,"y":0.6773504},{"x":0.26262626,"y":0.6773504},{"x":0.26262626,"y":0.70726496},{"x":0.24242425,"y":0.70726496}]},"symbols":[{"text":"(","confidence":0.8609917}],"confidence":0.8609917},{"property":{"detectedLanguages":[{"languageCode":"ta","confidence":1}]},"boundingBox":{"normalizedVertices":[{"x":0.26767677,"y":0.6773504},{"x":0.3409091,"y":0.6773504},{"x":0.3409091,"y":0.70726496},{"x":0.26767677,"y":0.70726496}]},"symbols":[{"text":"மு","confidence":0.9080969},{"text":"மு","confidence":0.8052218},{"text":"க்ஷ","confidence":0.89874965}],"confidence":0.87068945},{"property":{"detectedLanguages":[{"languageCode":"ta","confidence":1}]},"boundingBox":{"normalizedVertices":[{"x":0.36363637,"y":0.6773504},{"x":0.3989899,"y":0.6773504},{"x":0.3989899,"y":0.70726496},{"x":0.36363637,"y":0.70726496}]},"symbols":[{"property":{"detectedBreak":{"type":"SPACE"}},"text":")","confidence":0.9612217}],"confidence":0.9612217},{"property":{"detectedLanguages":[{"languageCode":"ta","confidence":1}]},"boundingBox":{"normalizedVertices":[{"x":0.41414142,"y":0.6773504},{"x":0.56565654,"y":0.6773504},{"x":0.56565654,"y":0.70726496},{"x":0.41414142,"y":0.70726496}]},"symbols":[{"text":"செ","confidence":0.9954734},{"text":"ய்ய","confidence":0.99634504},{"text":"த்த","confidence":0.9954841},{"property":{"detectedBreak":{"type":"SPACE"}},"text":"க்க","confidence":0.9930109}],"confidence":0.9950783},{"property":{"detectedLanguages":[{"languageCode":"ta","confidence":1}]},"boundingBox":{"normalizedVertices":[{"x":0.58838385,"y":0.6773504},{"x":0.7020202,"y":0.6773504},{"x":0.7020202,"y":0.70726496},{"x":0.58838385,"y":0.70726496}]},"symbols":[{"text":"க","confidence":0.9967528},{"text":"ர்ம","confidence":0.98835033},{"property":{"detectedBreak":{"type":"SPACE"}},"text":"த்தை","confidence":0.9746744}],"confidence":0.98659253},{"property":{"detectedLanguages":[{"languageCode":"ta","confidence":1}]},"boundingBox":{"normalizedVertices":[{"x":0.7222222,"y":0.6773504},{"x":0.8459596,"y":0.6773504},{"x":0.8459596,"y":0.70726496},{"x":0.7222222,"y":0.70726496}]},"symbols":[{"text":"அ","confidence":0.9943386},{"text":"டி","confidence":0.99282956},{"text":"யோ","confidence":0.9817522},{"property":{"detectedBreak":{"type":"EOL_SURE_SPACE"}},"text":"டு","confidence":0.9963569}],"confidence":0.9913193},{"property":{"detectedLanguages":[{"languageCode":"ta","confidence":1}]},"boundingBox":{"normalizedVertices":[{"x":0.7676768,"y":0.7094017},{"x":0.7752525,"y":0.7094017},{"x":0.7752525,"y":0.73504275},{"x":0.7676768,"y":0.73504275}]},"symbols":[{"text":"(","confidence":0.9719266}],"confidence":0.9719266},{"property":{"detectedLanguages":[{"languageCode":"ta","confidence":1}]},"boundingBox":{"normalizedVertices":[{"x":0.7828283,"y":0.7094017},{"x":0.7929293,"y":0.7094017},{"x":0.7929293,"y":0.73504275},{"x":0.7828283,"y":0.73504275}]},"symbols":[{"text":"எ","confidence":0.9878638}],"confidence":0.9878638},{"property":{"detectedLanguages":[{"languageCode":"ta","confidence":1}]},"boundingBox":{"normalizedVertices":[{"x":0.79545456,"y":0.7094017},{"x":0.8080808,"y":0.7094017},{"x":0.8080808,"y":0.73504275},{"x":0.79545456,"y":0.73504275}]},"symbols":[{"text":"-","confidence":0.97385484}],"confidence":0.97385484},{"property":{"detectedLanguages":[{"languageCode":"ta","confidence":1}]},"boundingBox":{"normalizedVertices":[{"x":0.81565654,"y":0.7094017},{"x":0.8308081,"y":0.7094017},{"x":0.8308081,"y":0.73504275},{"x":0.81565654,"y":0.73504275}]},"symbols":[{"text":"று","confidence":0.98442906}],"confidence":0.98442906},{"property":{"detectedLanguages":[{"languageCode":"ta","confidence":1}]},"boundingBox":{"normalizedVertices":[{"x":0.8358586,"y":0.7094017},{"x":0.8459596,"y":0.7094017},{"x":0.8459596,"y":0.73504275},{"x":0.8358586,"y":0.73504275}]},"symbols":[{"property":{"detectedBreak":{"type":"LINE_BREAK"}},"text":")","confidence":0.9357612}],"confidence":0.9357612}],"confidence":0.96931666}],"blockType":"TEXT","confidence":0.9577217},{"boundingBox":{"normalizedVertices":[{"x":0.17171717,"y":0.7094017},{"x":0.33838382,"y":0.71153843},{"x":0.33838382,"y":0.7307692},{"x":0.17171717,"y":0.72863245}]},"paragraphs":[{"boundingBox":{"normalizedVertices":[{"x":0.17171717,"y":0.7094017},{"x":0.33838382,"y":0.71153843},{"x":0.33838382,"y":0.7307692},{"x":0.17171717,"y":0.72863245}]},"words":[{"property":{"detectedLanguages":[{"languageCode":"ta","confidence":1}]},"boundingBox":{"normalizedVertices":[{"x":0.17171717,"y":0.7094017},{"x":0.32828283,"y":0.71153843},{"x":0.32828283,"y":0.7307692},{"x":0.17171717,"y":0.72863245}]},"symbols":[{"text":"வி","confidence":0.97100925},{"text":"ட","confidence":0.98448277},{"text":"வே","confidence":0.9712763},{"text":"ண்டு","confidence":0.9827544},{"text":"ம்","confidence":0.9959393}],"confidence":0.9810924},{"property":{"detectedLanguages":[{"languageCode":"ta","confidence":1}]},"boundingBox":{"normalizedVertices":[{"x":0.33080807,"y":0.71153843},{"x":0.33838382,"y":0.71153843},{"x":0.33838382,"y":0.7307692},{"x":0.33080807,"y":0.7307692}]},"symbols":[{"property":{"detectedBreak":{"type":"LINE_BREAK"}},"text":".","confidence":0.9797154}],"confidence":0.9797154}],"confidence":0.9808629}],"blockType":"TEXT","confidence":0.9808629},{"boundingBox":{"normalizedVertices":[{"x":0.17171717,"y":0.74786323},{"x":0.8459596,"y":0.74786323},{"x":0.8459596,"y":0.8333333},{"x":0.17171717,"y":0.8333333}]},"paragraphs":[{"boundingBox":{"normalizedVertices":[{"x":0.17171717,"y":0.74786323},{"x":0.8459596,"y":0.74786323},{"x":0.8459596,"y":0.8333333},{"x":0.17171717,"y":0.8333333}]},"words":[{"property":{"detectedLanguages":[{"languageCode":"ta","confidence":1}]},"boundingBox":{"normalizedVertices":[{"x":0.23232323,"y":0.74786323},{"x":0.37121212,"y":0.74786323},{"x":0.37121212,"y":0.77350426},{"x":0.23232323,"y":0.77350426}]},"symbols":[{"text":"கா","confidence":0.96318215},{"text":"ம்ய","confidence":0.9738967},{"text":"க","confidence":0.99442154},{"text":"ர்ம","confidence":0.99421096},{"property":{"detectedBreak":{"type":"SPACE"}},"text":"ம்","confidence":0.99839324}],"confidence":0.9848209},{"property":{"detectedLanguages":[{"languageCode":"ta","confidence":1}]},"boundingBox":{"normalizedVertices":[{"x":0.3838384,"y":0.74786323},{"x":0.47727272,"y":0.74786323},{"x":0.47727272,"y":0.77350426},{"x":0.3838384,"y":0.77350426}]},"symbols":[{"text":"மு","confidence":0.995034},{"text":"ற்று","confidence":0.9919576},{"property":{"detectedBreak":{"type":"SPACE"}},"text":"ம்","confidence":0.9963913}],"confidence":0.99446094},{"property":{"detectedLanguages":[{"languageCode":"ta","confidence":1}]},"boundingBox":{"normalizedVertices":[{"x":0.48989898,"y":0.74786323},{"x":0.739899,"y":0.74786323},{"x":0.739899,"y":0.77350426},{"x":0.48989898,"y":0.77350426}]},"symbols":[{"text":"வி","confidence":0.9954138},{"text":"ட","confidence":0.9920039},{"text":"வே","confidence":0.9690291},{"text":"ண்டி","confidence":0.97966355},{"text":"ய","confidence":0.9944016},{"text":"தே","confidence":0.9876351},{"text":"யா","confidence":0.98768467},{"text":"ம்","confidence":0.9907508}],"confidence":0.9870728},{"property":{"detectedLanguages":[{"languageCode":"ta","confidence":1}]},"boundingBox":{"normalizedVertices":[{"x":0.74242425,"y":0.74786323},{"x":0.74747473,"y":0.74786323},{"x":0.74747473,"y":0.77350426},{"x":0.74242425,"y":0.77350426}]},"symbols":[{"property":{"detectedBreak":{"type":"SPACE"}},"text":".","confidence":0.9872728}],"confidence":0.9872728},{"property":{"detectedLanguages":[{"languageCode":"ta","confidence":1}]},"boundingBox":{"normalizedVertices":[{"x":0.7676768,"y":0.74786323},{"x":0.8459596,"y":0.74786323},{"x":0.8459596,"y":0.77350426},{"x":0.7676768,"y":0.77350426}]},"symbols":[{"text":"நி","confidence":0.98599166},{"text":"த்தி","confidence":0.9801939},{"property":{"detectedBreak":{"type":"EOL_SURE_SPACE"}},"text":"ய","confidence":0.99316347}],"confidence":0.98644966},{"property":{"detectedLanguages":[{"languageCode":"ta","confidence":1}]},"boundingBox":{"normalizedVertices":[{"x":0.17171717,"y":0.7777778},{"x":0.34343433,"y":0.7777778},{"x":0.34343433,"y":0.8034188},{"x":0.17171717,"y":0.8034188}]},"symbols":[{"text":"நை","confidence":0.95259786},{"text":"மி","confidence":0.9937303},{"text":"த்தி","confidence":0.99631345},{"text":"க","confidence":0.9984712},{"text":"மு","confidence":0.9985741},{"property":{"detectedBreak":{"type":"SPACE"}},"text":"ம்","confidence":0.99870014}],"confidence":0.9897312},{"property":{"detectedLanguages":[{"languageCode":"ta","confidence":1}]},"boundingBox":{"normalizedVertices":[{"x":0.35858586,"y":0.7777778},{"x":0.48232323,"y":0.7777778},{"x":0.48232323,"y":0.8034188},{"x":0.35858586,"y":0.8034188}]},"symbols":[{"text":"சி","confidence":0.9976319},{"text":"த்த","confidence":0.9863024},{"text":"சு","confidence":0.99273187},{"property":{"detectedBreak":{"type":"SPACE"}},"text":"த்தி","confidence":0.99043065}],"confidence":0.9917742},{"property":{"detectedLanguages":[{"languageCode":"ta","confidence":1}]},"boundingBox":{"normalizedVertices":[{"x":0.5,"y":0.7777778},{"x":0.52020204,"y":0.7777778},{"x":0.52020204,"y":0.8034188},{"x":0.5,"y":0.8034188}]},"symbols":[{"text":"(","confidence":0.98272383}],"confidence":0.98272383},{"property":{"detectedLanguages":[{"languageCode":"ta","confidence":1}]},"boundingBox":{"normalizedVertices":[{"x":0.52272725,"y":0.7777778},{"x":0.6792929,"y":0.7777778},{"x":0.6792929,"y":0.8034188},{"x":0.52272725,"y":0.8034188}]},"symbols":[{"text":"ம","confidence":0.9938394},{"text":"ன","confidence":0.989692},{"text":"த்தூ","confidence":0.9772867},{"text":"ய்மை","confidence":0.97105557}],"confidence":0.9829684},{"property":{"detectedLanguages":[{"languageCode":"ta","confidence":1}]},"boundingBox":{"normalizedVertices":[{"x":0.68434346,"y":0.7777778},{"x":0.6919192,"y":0.7777778},{"x":0.6919192,"y":0.8034188},{"x":0.68434346,"y":0.8034188}]},"symbols":[{"property":{"detectedBreak":{"type":"SPACE"}},"text":")","confidence":0.96291983}],"confidence":0.96291983},{"property":{"detectedLanguages":[{"languageCode":"ta","confidence":1}]},"boundingBox":{"normalizedVertices":[{"x":0.7121212,"y":0.7777778},{"x":0.8459596,"y":0.7777778},{"x":0.8459596,"y":0.8034188},{"x":0.7121212,"y":0.8034188}]},"symbols":[{"text":"வ","confidence":0.99244803},{"text":"ரு","confidence":0.99234504},{"text":"ம","confidence":0.99358845},{"text":"ள","confidence":0.99425405},{"text":"வு","confidence":0.9959818},{"property":{"detectedBreak":{"type":"EOL_SURE_SPACE"}},"text":"ம்","confidence":0.9894234}],"confidence":0.9930068},{"property":{"detectedLanguages":[{"languageCode":"ta","confidence":1}]},"boundingBox":{"normalizedVertices":[{"x":0.17171717,"y":0.8055556},{"x":0.44191918,"y":0.8055556},{"x":0.44191918,"y":0.8333333},{"x":0.17171717,"y":0.8333333}]},"symbols":[{"text":"செ","confidence":0.9828078},{"text":"ய்ய","confidence":0.9933874},{"text":"த்த","confidence":0.9959361},{"text":"க்க","confidence":0.9947387},{"text":"ன","confidence":0.9946714},{"text":"வே","confidence":0.9877065},{"text":"யா","confidence":0.9897205},{"property":{"detectedBreak":{"type":"SPACE"}},"text":"ம்","confidence":0.988747}],"confidence":0.9909644},{"property":{"detectedLanguages":[{"languageCode":"ta","confidence":1}]},"boundingBox":{"normalizedVertices":[{"x":0.4520202,"y":0.8055556},{"x":0.45959595,"y":0.8055556},{"x":0.45959595,"y":0.8333333},{"x":0.4520202,"y":0.8333333}]},"symbols":[{"property":{"detectedBreak":{"type":"SPACE"}},"text":";","confidence":0.9524455}],"confidence":0.9524455},{"property":{"detectedLanguages":[{"languageCode":"ta","confidence":1}]},"boundingBox":{"normalizedVertices":[{"x":0.47474748,"y":0.8055556},{"x":0.55050504,"y":0.8055556},{"x":0.55050504,"y":0.8333333},{"x":0.47474748,"y":0.8333333}]},"symbols":[{"text":"அ","confidence":0.9960817},{"text":"த","confidence":0.99861145},{"property":{"detectedBreak":{"type":"SPACE"}},"text":"ன்","confidence":0.9983259}],"confidence":0.99767303},{"property":{"detectedLanguages":[{"languageCode":"ta","confidence":1}]},"boundingBox":{"normalizedVertices":[{"x":0.56313133,"y":0.8055556},{"x":0.68434346,"y":0.8055556},{"x":0.68434346,"y":0.8333333},{"x":0.56313133,"y":0.8333333}]},"symbols":[{"text":"பி","confidence":0.9977414},{"text":"ன்ன","confidence":0.9955136},{"text":"ரு","confidence":0.99408644},{"property":{"detectedBreak":{"type":"SPACE"}},"text":"ம்","confidence":0.9963428}],"confidence":0.9959211},{"property":{"detectedLanguages":[{"languageCode":"ta","confidence":1}]},"boundingBox":{"normalizedVertices":[{"x":0.6969697,"y":0.8055556},{"x":0.8459596,"y":0.8055556},{"x":0.8459596,"y":0.8333333},{"x":0.6969697,"y":0.8333333}]},"symbols":[{"text":"பி","confidence":0.98481107},{"text":"ர","confidence":0.9901974},{"text":"ஹ்ம","confidence":0.9404281},{"text":"த்தி","confidence":0.9937049},{"property":{"detectedBreak":{"type":"LINE_BREAK"}},"text":"ல்","confidence":0.9912349}],"confidence":0.9800753}],"confidence":0.98807895}],"blockType":"TEXT","confidence":0.98807895}],"confidence":0.8797961}],"text":":\nஸ்ரீ ராமகீதை.\nஉ\nதின்) உற்பத்தியில் சித்தசுத்திவாயிலாகக் கர்மாபேக்ஷை\nயாம். தனது பயனை உண்டு பண்ணுந்தன்மையில் அக்கர்\nமத்தின் அபேக்ஷையின் றியதேயாம். அப்படிக்கில்லையா\nயின், வித்தையின் சொரூபத்திற்கே பங்கம் வருமாகலின்\nஎன்பதனால் பூர்வபக்ஷி கூறிய ஏது சித்தியாததாம் என்\nபது கருத்து.\n(கரு)\nतस्मात्त्यजेत्कार्यमशेषतः सुधीर्विद्याविरोधान्न समुच्चयो भवेत् !\nआत्मानुसंधानपरायणः सदा निवृत्त सर्वेन्द्रियवृत्तिगोचरः ॥ १६ ॥\n(அ-கை.) முற்கூறியதனை முடித்து முமுக்ஷவினது\nவிருத்தியின்றன்மையினைக் கூறுகின்றார்:-\nविद्याविरोधात् समुच्चयः न भवेत् तस्मात् सुधीः अशेषतः\nकार्यम् त्यजेत् ॥\n(இ-ள்) வித்தைக்கு (கர்மத்தோடு) விரோத மிருத்\nதலால் சமுச்சய முண்டாகாது. ஆதலால் நற்புத்தியுடை\nயோன் (முமுக்ஷ) செய்யத்தக்க கர்மத்தை அடியோடு\n(எ-று)\nவிடவேண்டும்.\nகாம்யகர்மம் முற்றும் விடவேண்டியதேயாம். நித்திய\nநைமித்திகமும் சித்தசுத்தி (மனத்தூய்மை) வருமளவும்\nசெய்யத்தக்கனவேயாம் ; அதன் பின்னரும் பிரஹ்மத்தில்"},"context":{"uri":"gs://iiith-ska-satamt/ocr/src/ramagitai/ramagitai.pdf","pageNumber":31}}]}