{"inputConfig":{"gcsSource":{"uri":"gs://iiith-ska-satamt/ocr/src/ramagitai/ramagitai.pdf"},"mimeType":"application/pdf"},"responses":[{"fullTextAnnotation":{"pages":[{"property":{"detectedLanguages":[{"languageCode":"ta","confidence":0.75921273},{"languageCode":"sa","confidence":0.22552189}]},"width":396,"height":468,"blocks":[{"boundingBox":{"normalizedVertices":[{"x":0.42676768,"y":0.09615385},{"x":0.5681818,"y":0.09615385},{"x":0.5681818,"y":0.12820514},{"x":0.42676768,"y":0.12820514}]},"paragraphs":[{"boundingBox":{"normalizedVertices":[{"x":0.42676768,"y":0.09615385},{"x":0.5681818,"y":0.09615385},{"x":0.5681818,"y":0.12820514},{"x":0.42676768,"y":0.12820514}]},"words":[{"property":{"detectedLanguages":[{"languageCode":"ta","confidence":1}]},"boundingBox":{"normalizedVertices":[{"x":0.42676768,"y":0.09615385},{"x":0.44949496,"y":0.09615385},{"x":0.44949496,"y":0.12820514},{"x":0.42676768,"y":0.12820514}]},"symbols":[{"property":{"detectedBreak":{"type":"SPACE"}},"text":"ஸ்ரீ","confidence":0.8327962}],"confidence":0.8327962},{"property":{"detectedLanguages":[{"languageCode":"ta","confidence":1}]},"boundingBox":{"normalizedVertices":[{"x":0.46717173,"y":0.09615385},{"x":0.56060606,"y":0.09615385},{"x":0.56060606,"y":0.12820514},{"x":0.46717173,"y":0.12820514}]},"symbols":[{"text":"ரா","confidence":0.96413624},{"text":"ம","confidence":0.98408806},{"text":"கீ","confidence":0.8147721},{"text":"தை","confidence":0.98623294}],"confidence":0.93730736},{"property":{"detectedLanguages":[{"languageCode":"ta","confidence":1}]},"boundingBox":{"normalizedVertices":[{"x":0.56060606,"y":0.09615385},{"x":0.5681818,"y":0.09615385},{"x":0.5681818,"y":0.12820514},{"x":0.56060606,"y":0.12820514}]},"symbols":[{"property":{"detectedBreak":{"type":"LINE_BREAK"}},"text":".","confidence":0.9677229}],"confidence":0.9677229}],"confidence":0.9249581}],"blockType":"TEXT","confidence":0.9249581},{"boundingBox":{"normalizedVertices":[{"x":0.7929293,"y":0.09615385},{"x":0.82828283,"y":0.09615385},{"x":0.82828283,"y":0.115384616},{"x":0.7929293,"y":0.115384616}]},"paragraphs":[{"boundingBox":{"normalizedVertices":[{"x":0.7929293,"y":0.09615385},{"x":0.82828283,"y":0.09615385},{"x":0.82828283,"y":0.115384616},{"x":0.7929293,"y":0.115384616}]},"words":[{"boundingBox":{"normalizedVertices":[{"x":0.7929293,"y":0.09615385},{"x":0.82828283,"y":0.09615385},{"x":0.82828283,"y":0.115384616},{"x":0.7929293,"y":0.115384616}]},"symbols":[{"text":"ரு","confidence":0.8622612},{"property":{"detectedBreak":{"type":"LINE_BREAK"}},"text":"எ","confidence":0.963982}],"confidence":0.9131216}],"confidence":0.9131216}],"blockType":"TEXT","confidence":0.9131216},{"boundingBox":{"normalizedVertices":[{"x":0.1590909,"y":0.15170941},{"x":0.8308081,"y":0.14529915},{"x":0.83838385,"y":0.61752135},{"x":0.16666667,"y":0.62606835}]},"paragraphs":[{"boundingBox":{"normalizedVertices":[{"x":0.16666667,"y":0.15170941},{"x":0.8308081,"y":0.1474359},{"x":0.8308081,"y":0.21581197},{"x":0.16666667,"y":0.22008547}]},"words":[{"property":{"detectedLanguages":[{"languageCode":"sa","confidence":1}]},"boundingBox":{"normalizedVertices":[{"x":0.20707071,"y":0.15170941},{"x":0.26262626,"y":0.15170941},{"x":0.26262626,"y":0.17948718},{"x":0.20707071,"y":0.18162394}]},"symbols":[{"text":"ए","confidence":0.8991487},{"text":"क","confidence":0.8708577},{"property":{"detectedBreak":{"type":"SPACE"}},"text":"त्र","confidence":0.9026566}],"confidence":0.8908877},{"property":{"detectedLanguages":[{"languageCode":"sa","confidence":1}]},"boundingBox":{"normalizedVertices":[{"x":0.27272728,"y":0.15170941},{"x":0.3409091,"y":0.15170941},{"x":0.3409091,"y":0.17948718},{"x":0.27272728,"y":0.17948718}]},"symbols":[{"text":"वा","confidence":0.91223466},{"text":"सा","confidence":0.8925716},{"property":{"detectedBreak":{"type":"SPACE"}},"text":"त्","confidence":0.8700473}],"confidence":0.89161783},{"property":{"detectedLanguages":[{"languageCode":"sa","confidence":1}]},"boundingBox":{"normalizedVertices":[{"x":0.34848484,"y":0.15170941},{"x":0.5126263,"y":0.14957266},{"x":0.5126263,"y":0.17735043},{"x":0.34848484,"y":0.17948718}]},"symbols":[{"text":"अ","confidence":0.94148403},{"text":"न","confidence":0.9461032},{"text":"ला","confidence":0.834198},{"text":"त","confidence":0.8073408},{"text":"लो","confidence":0.9093944},{"text":"ह","confidence":0.93012244},{"text":"व","confidence":0.9074805},{"property":{"detectedBreak":{"type":"SPACE"}},"text":"त्","confidence":0.9589908}],"confidence":0.90438926},{"property":{"detectedLanguages":[{"languageCode":"sa","confidence":1}]},"boundingBox":{"normalizedVertices":[{"x":0.5151515,"y":0.14957266},{"x":0.7449495,"y":0.1474359},{"x":0.7449495,"y":0.17521368},{"x":0.5151515,"y":0.17735043}]},"symbols":[{"text":"चि","confidence":0.9473497},{"text":"ह्नि","confidence":0.5074602},{"text":"म्ब","confidence":0.9045613},{"text":"सा","confidence":0.92732406},{"text":"क्षा","confidence":0.9023467},{"text":"त्म","confidence":0.925696},{"text":"धि","confidence":0.7991188},{"text":"या","confidence":0.8638428},{"property":{"detectedBreak":{"type":"SPACE"}},"text":"म्","confidence":0.81208134}],"confidence":0.843309},{"property":{"detectedLanguages":[{"languageCode":"sa","confidence":1}]},"boundingBox":{"normalizedVertices":[{"x":0.75,"y":0.1474359},{"x":0.8308081,"y":0.1474359},{"x":0.8308081,"y":0.17521368},{"x":0.75,"y":0.17521368}]},"symbols":[{"text":"प्र","confidence":0.9299934},{"text":"स","confidence":0.9474642},{"text":"ङ्ग","confidence":0.93516654},{"property":{"detectedBreak":{"type":"EOL_SURE_SPACE"}},"text":"तः","confidence":0.8724109}],"confidence":0.92125875},{"property":{"detectedLanguages":[{"languageCode":"sa","confidence":1}]},"boundingBox":{"normalizedVertices":[{"x":0.16666667,"y":0.18803419},{"x":0.3131313,"y":0.18803419},{"x":0.3131313,"y":0.21794872},{"x":0.16666667,"y":0.22008547}]},"symbols":[{"text":"चि","confidence":0.8937869},{"text":"दा","confidence":0.9440915},{"text":"त्म","confidence":0.94867134},{"text":"चे","confidence":0.9131479},{"text":"त","confidence":0.95494556},{"property":{"detectedBreak":{"type":"SPACE"}},"text":"सोः","confidence":0.85919094}],"confidence":0.9189724},{"property":{"detectedLanguages":[{"languageCode":"sa","confidence":1}]},"boundingBox":{"normalizedVertices":[{"x":0.32828283,"y":0.18803419},{"x":0.42676768,"y":0.18803419},{"x":0.42676768,"y":0.21794872},{"x":0.32828283,"y":0.21794872}]},"symbols":[{"text":"अ","confidence":0.973144},{"text":"न्यो","confidence":0.9405705},{"text":"न्य","confidence":0.95563024},{"property":{"detectedBreak":{"type":"SPACE"}},"text":"म्","confidence":0.94891536}],"confidence":0.95456505},{"property":{"detectedLanguages":[{"languageCode":"sa","confidence":1}]},"boundingBox":{"normalizedVertices":[{"x":0.43939394,"y":0.18803419},{"x":0.5808081,"y":0.18589744},{"x":0.5808081,"y":0.21581197},{"x":0.43939394,"y":0.21794872}]},"symbols":[{"text":"अ","confidence":0.9624196},{"text":"ध्या","confidence":0.8707859},{"text":"स","confidence":0.9590569},{"text":"व","confidence":0.9400102},{"text":"शा","confidence":0.94209135},{"property":{"detectedBreak":{"type":"SPACE"}},"text":"त्","confidence":0.96890265}],"confidence":0.9405444},{"property":{"detectedLanguages":[{"languageCode":"sa","confidence":1}]},"boundingBox":{"normalizedVertices":[{"x":0.58838385,"y":0.18589744},{"x":0.71464646,"y":0.18589744},{"x":0.71464646,"y":0.21581197},{"x":0.58838385,"y":0.21794872}]},"symbols":[{"text":"ज","confidence":0.96757877},{"text":"डा","confidence":0.8697686},{"text":"ज","confidence":0.9107541},{"text":"ड","confidence":0.9368384},{"text":"त्व","confidence":0.94471645},{"property":{"detectedBreak":{"type":"SPACE"}},"text":"म्","confidence":0.96707684}],"confidence":0.93278885},{"property":{"detectedLanguages":[{"languageCode":"sa","confidence":1}]},"boundingBox":{"normalizedVertices":[{"x":0.72979796,"y":0.18589744},{"x":0.8030303,"y":0.18589744},{"x":0.8030303,"y":0.21581197},{"x":0.72979796,"y":0.21581197}]},"symbols":[{"text":"प्र","confidence":0.962233},{"text":"ती","confidence":0.9348753},{"text":"य","confidence":0.9722854},{"property":{"detectedBreak":{"type":"SPACE"}},"text":"ते","confidence":0.93205965}],"confidence":0.95036334},{"property":{"detectedLanguages":[{"languageCode":"sa","confidence":1}]},"boundingBox":{"normalizedVertices":[{"x":0.81565654,"y":0.18589744},{"x":0.8207071,"y":0.18589744},{"x":0.8207071,"y":0.21581197},{"x":0.81565654,"y":0.21581197}]},"symbols":[{"property":{"detectedBreak":{"type":"LINE_BREAK"}},"text":"॥","confidence":0.71594924}],"confidence":0.71594924}],"confidence":0.9064249},{"boundingBox":{"normalizedVertices":[{"x":0.16666667,"y":0.24358974},{"x":0.8308081,"y":0.23931624},{"x":0.8333333,"y":0.42307693},{"x":0.16666667,"y":0.42948717}]},"words":[{"property":{"detectedLanguages":[{"languageCode":"ta","confidence":1}]},"boundingBox":{"normalizedVertices":[{"x":0.22979797,"y":0.24358974},{"x":0.24242425,"y":0.24358974},{"x":0.24242425,"y":0.2735043},{"x":0.22979797,"y":0.2735043}]},"symbols":[{"text":"(","confidence":0.93574506}],"confidence":0.93574506},{"property":{"detectedLanguages":[{"languageCode":"ta","confidence":1}]},"boundingBox":{"normalizedVertices":[{"x":0.24494949,"y":0.24358974},{"x":0.25757575,"y":0.24358974},{"x":0.25757575,"y":0.2735043},{"x":0.24494949,"y":0.2735043}]},"symbols":[{"text":"இ","confidence":0.9741385}],"confidence":0.9741385},{"property":{"detectedLanguages":[{"languageCode":"ta","confidence":1}]},"boundingBox":{"normalizedVertices":[{"x":0.26262626,"y":0.24358974},{"x":0.2777778,"y":0.24358974},{"x":0.2777778,"y":0.2735043},{"x":0.26262626,"y":0.2735043}]},"symbols":[{"text":"-","confidence":0.9825022}],"confidence":0.9825022},{"property":{"detectedLanguages":[{"languageCode":"ta","confidence":1}]},"boundingBox":{"normalizedVertices":[{"x":0.28282827,"y":0.24358974},{"x":0.2979798,"y":0.24358974},{"x":0.2979798,"y":0.2735043},{"x":0.28282827,"y":0.2735043}]},"symbols":[{"text":"ள்","confidence":0.9929077}],"confidence":0.9929077},{"property":{"detectedLanguages":[{"languageCode":"ta","confidence":1}]},"boundingBox":{"normalizedVertices":[{"x":0.30555555,"y":0.24358974},{"x":0.3181818,"y":0.24358974},{"x":0.3181818,"y":0.2735043},{"x":0.30555555,"y":0.2735043}]},"symbols":[{"property":{"detectedBreak":{"type":"SPACE"}},"text":")","confidence":0.9909357}],"confidence":0.9909357},{"property":{"detectedLanguages":[{"languageCode":"ta","confidence":1}]},"boundingBox":{"normalizedVertices":[{"x":0.35353535,"y":0.24358974},{"x":0.46464646,"y":0.24145299},{"x":0.46717173,"y":0.27136752},{"x":0.35353535,"y":0.2735043}]},"symbols":[{"text":"ஓ","confidence":0.9649978},{"text":"ரி","confidence":0.99009275},{"text":"ட","confidence":0.99612993},{"text":"த்தி","confidence":0.99539983},{"property":{"detectedBreak":{"type":"SPACE"}},"text":"ல்","confidence":0.9979872}],"confidence":0.9889215},{"property":{"detectedLanguages":[{"languageCode":"ta","confidence":1}]},"boundingBox":{"normalizedVertices":[{"x":0.48989898,"y":0.24145299},{"x":0.6212121,"y":0.24145299},{"x":0.6212121,"y":0.27136752},{"x":0.48989898,"y":0.27136752}]},"symbols":[{"text":"வ","confidence":0.9985503},{"text":"சி","confidence":0.9987057},{"text":"த்த","confidence":0.99425},{"text":"லா","confidence":0.9734026},{"property":{"detectedBreak":{"type":"SPACE"}},"text":"ல்","confidence":0.97648543}],"confidence":0.9882788},{"property":{"detectedLanguages":[{"languageCode":"ta","confidence":1}]},"boundingBox":{"normalizedVertices":[{"x":0.6388889,"y":0.24145299},{"x":0.6489899,"y":0.24145299},{"x":0.6489899,"y":0.27136752},{"x":0.6388889,"y":0.27136752}]},"symbols":[{"property":{"detectedBreak":{"type":"SPACE"}},"text":"*","confidence":0.90073}],"confidence":0.90073},{"property":{"detectedLanguages":[{"languageCode":"ta","confidence":1}]},"boundingBox":{"normalizedVertices":[{"x":0.6666667,"y":0.24145299},{"x":0.74747473,"y":0.24145299},{"x":0.74747473,"y":0.27136752},{"x":0.6666667,"y":0.27136752}]},"symbols":[{"text":"அ","confidence":0.9776485},{"text":"ந","confidence":0.9269356},{"text":"லி","confidence":0.794892},{"property":{"detectedBreak":{"type":"SPACE"}},"text":"ற்","confidence":0.95581394}],"confidence":0.91382253},{"property":{"detectedLanguages":[{"languageCode":"ta","confidence":1}]},"boundingBox":{"normalizedVertices":[{"x":0.74747473,"y":0.24145299},{"x":0.82828283,"y":0.23931624},{"x":0.8308081,"y":0.26923078},{"x":0.74747473,"y":0.27136752}]},"symbols":[{"text":"கா","confidence":0.9593173},{"property":{"detectedBreak":{"type":"EOL_SURE_SPACE"}},"text":"ய்ந்த","confidence":0.97534454}],"confidence":0.96733093},{"property":{"detectedLanguages":[{"languageCode":"ta","confidence":1}]},"boundingBox":{"normalizedVertices":[{"x":0.16666667,"y":0.2777778},{"x":0.38131315,"y":0.27564102},{"x":0.38131315,"y":0.30341882},{"x":0.16666667,"y":0.30769232}]},"symbols":[{"text":"இ","confidence":0.9845604},{"text":"ரு","confidence":0.9859253},{"text":"ம்பி","confidence":0.9667663},{"text":"னை","confidence":0.96215457},{"text":"ப்போ","confidence":0.9498748},{"text":"ல","confidence":0.99357074}],"confidence":0.9738087},{"property":{"detectedLanguages":[{"languageCode":"ta","confidence":1}]},"boundingBox":{"normalizedVertices":[{"x":0.3838384,"y":0.27564102},{"x":0.39141414,"y":0.27564102},{"x":0.39141414,"y":0.30341882},{"x":0.3838384,"y":0.30341882}]},"symbols":[{"property":{"detectedBreak":{"type":"SPACE"}},"text":",","confidence":0.9858876}],"confidence":0.9858876},{"property":{"detectedLanguages":[{"languageCode":"ta","confidence":1}]},"boundingBox":{"normalizedVertices":[{"x":0.39646465,"y":0.27564102},{"x":0.5833333,"y":0.2735043},{"x":0.5833333,"y":0.30128205},{"x":0.3989899,"y":0.30341882}]},"symbols":[{"text":"சி","confidence":0.9837776},{"text":"ற்பி","confidence":0.9266015},{"text":"ர","confidence":0.9777514},{"text":"தி","confidence":0.959251},{"text":"பி","confidence":0.9909264},{"text":"ம்ப","confidence":0.99289596},{"property":{"detectedBreak":{"type":"SPACE"}},"text":"ம்","confidence":0.99761254}],"confidence":0.97554517},{"property":{"detectedLanguages":[{"languageCode":"ta","confidence":1}]},"boundingBox":{"normalizedVertices":[{"x":0.59090906,"y":0.2735043},{"x":0.8308081,"y":0.27136752},{"x":0.8308081,"y":0.2991453},{"x":0.59090906,"y":0.30128205}]},"symbols":[{"text":"இ","confidence":0.9965888},{"text":"ந்தி","confidence":0.97378755},{"text":"ரி","confidence":0.9757296},{"text":"ய","confidence":0.9912175},{"text":"ங்க","confidence":0.9893488},{"text":"ளோ","confidence":0.986712},{"text":"டு","confidence":0.98582697},{"property":{"detectedBreak":{"type":"EOL_SURE_SPACE"}},"text":"கூ","confidence":0.8895708}],"confidence":0.97359776},{"property":{"detectedLanguages":[{"languageCode":"ta","confidence":1}]},"boundingBox":{"normalizedVertices":[{"x":0.16919191,"y":0.30982906},{"x":0.20707071,"y":0.30982906},{"x":0.20959596,"y":0.33760685},{"x":0.16919191,"y":0.33760685}]},"symbols":[{"text":"டி","confidence":0.9717416},{"property":{"detectedBreak":{"type":"SPACE"}},"text":"ய","confidence":0.9849692}],"confidence":0.9783554},{"property":{"detectedLanguages":[{"languageCode":"ta","confidence":1}]},"boundingBox":{"normalizedVertices":[{"x":0.22222222,"y":0.30982906},{"x":0.2929293,"y":0.30769232},{"x":0.2929293,"y":0.33547008},{"x":0.22222222,"y":0.33760685}]},"symbols":[{"text":"ம","confidence":0.98923886},{"text":"ன","confidence":0.99432},{"property":{"detectedBreak":{"type":"SPACE"}},"text":"து","confidence":0.9927769}],"confidence":0.9921119},{"property":{"detectedLanguages":[{"languageCode":"ta","confidence":1}]},"boundingBox":{"normalizedVertices":[{"x":0.3131313,"y":0.30769232},{"x":0.47727272,"y":0.30555555},{"x":0.47727272,"y":0.33547008},{"x":0.3131313,"y":0.33760685}]},"symbols":[{"text":"அ","confidence":0.9957166},{"text":"ந்த","confidence":0.99391013},{"text":"க்க","confidence":0.99303937},{"text":"ர","confidence":0.9981916},{"text":"ண","confidence":0.99845505},{"property":{"detectedBreak":{"type":"SPACE"}},"text":"ம்","confidence":0.998541}],"confidence":0.9963089},{"property":{"detectedLanguages":[{"languageCode":"ta","confidence":1}]},"boundingBox":{"normalizedVertices":[{"x":0.49747476,"y":0.30555555},{"x":0.6515151,"y":0.30341882},{"x":0.6515151,"y":0.33333334},{"x":0.49747476,"y":0.33333334}]},"symbols":[{"text":"எ","confidence":0.98786324},{"text":"ன்ப","confidence":0.9415657},{"text":"வ","confidence":0.9861422},{"text":"ற்றி","confidence":0.98787373},{"property":{"detectedBreak":{"type":"SPACE"}},"text":"ன்","confidence":0.9977141}],"confidence":0.9802318},{"property":{"detectedLanguages":[{"languageCode":"ta","confidence":1}]},"boundingBox":{"normalizedVertices":[{"x":0.6641414,"y":0.30341882},{"x":0.75252527,"y":0.30341882},{"x":0.75252527,"y":0.33119658},{"x":0.6641414,"y":0.33333334}]},"symbols":[{"text":"ச","confidence":0.995024},{"text":"மீ","confidence":0.9909879},{"text":"ப","confidence":0.9928966},{"property":{"detectedBreak":{"type":"SPACE"}},"text":"மா","confidence":0.98880243}],"confidence":0.99192774},{"property":{"detectedLanguages":[{"languageCode":"ta","confidence":1}]},"boundingBox":{"normalizedVertices":[{"x":0.7651515,"y":0.30341882},{"x":0.8308081,"y":0.30128205},{"x":0.8308081,"y":0.33119658},{"x":0.7676768,"y":0.33119658}]},"symbols":[{"text":"யி","confidence":0.9883899},{"text":"ரு","confidence":0.9909987},{"property":{"detectedBreak":{"type":"EOL_SURE_SPACE"}},"text":"த்","confidence":0.9713649}],"confidence":0.9835845},{"property":{"detectedLanguages":[{"languageCode":"ta","confidence":1}]},"boundingBox":{"normalizedVertices":[{"x":0.17171717,"y":0.33974358},{"x":0.20707071,"y":0.33974358},{"x":0.20707071,"y":0.3696581},{"x":0.17171717,"y":0.3696581}]},"symbols":[{"text":"த","confidence":0.98915964},{"property":{"detectedBreak":{"type":"SPACE"}},"text":"ல்","confidence":0.99531066}],"confidence":0.9922352},{"property":{"detectedLanguages":[{"languageCode":"ta","confidence":1}]},"boundingBox":{"normalizedVertices":[{"x":0.21717171,"y":0.33974358},{"x":0.35858586,"y":0.33760685},{"x":0.35858586,"y":0.3696581},{"x":0.21717171,"y":0.3696581}]},"symbols":[{"text":"கா","confidence":0.9881631},{"text":"ர","confidence":0.9964194},{"text":"ண","confidence":0.99669206},{"text":"மா","confidence":0.9923223},{"text":"க","confidence":0.9970382},{"property":{"detectedBreak":{"type":"SPACE"}},"text":"ச்","confidence":0.99569505}],"confidence":0.99438834},{"property":{"detectedLanguages":[{"languageCode":"ta","confidence":1}]},"boundingBox":{"normalizedVertices":[{"x":0.37373737,"y":0.33760685},{"x":0.5530303,"y":0.33760685},{"x":0.5530303,"y":0.36752138},{"x":0.37373737,"y":0.3696581}]},"symbols":[{"text":"சி","confidence":0.9887622},{"text":"தா","confidence":0.97043335},{"text":"த்மா","confidence":0.9746996},{"text":"வி","confidence":0.9815055},{"text":"லு","confidence":0.9734255},{"property":{"detectedBreak":{"type":"SPACE"}},"text":"ம்","confidence":0.9781067}],"confidence":0.9778221},{"property":{"detectedLanguages":[{"languageCode":"ta","confidence":1}]},"boundingBox":{"normalizedVertices":[{"x":0.5681818,"y":0.33760685},{"x":0.57828283,"y":0.33760685},{"x":0.57828283,"y":0.36752138},{"x":0.5681818,"y":0.36752138}]},"symbols":[{"text":"(","confidence":0.9914514}],"confidence":0.9914514},{"property":{"detectedLanguages":[{"languageCode":"ta","confidence":1}]},"boundingBox":{"normalizedVertices":[{"x":0.5808081,"y":0.33760685},{"x":0.7323232,"y":0.33547008},{"x":0.7323232,"y":0.3653846},{"x":0.5808081,"y":0.36752138}]},"symbols":[{"text":"ஜீ","confidence":0.9833052},{"text":"வ","confidence":0.98650867},{"text":"னி","confidence":0.992112},{"text":"ட","confidence":0.9968817},{"text":"த்து","confidence":0.99299306},{"text":"ம்","confidence":0.9952849}],"confidence":0.9911809},{"property":{"detectedLanguages":[{"languageCode":"ta","confidence":1}]},"boundingBox":{"normalizedVertices":[{"x":0.7373737,"y":0.33547008},{"x":0.7449495,"y":0.33547008},{"x":0.7449495,"y":0.3653846},{"x":0.7373737,"y":0.3653846}]},"symbols":[{"property":{"detectedBreak":{"type":"SPACE"}},"text":")","confidence":0.98328793}],"confidence":0.98328793},{"property":{"detectedLanguages":[{"languageCode":"ta","confidence":1}]},"boundingBox":{"normalizedVertices":[{"x":0.7550505,"y":0.33547008},{"x":0.8308081,"y":0.33547008},{"x":0.8308081,"y":0.3653846},{"x":0.75757575,"y":0.3653846}]},"symbols":[{"text":"சி","confidence":0.9887859},{"text":"த்த","confidence":0.98172724},{"property":{"detectedBreak":{"type":"EOL_SURE_SPACE"}},"text":"த்","confidence":0.90969414}],"confidence":0.9600691},{"property":{"detectedLanguages":[{"languageCode":"ta","confidence":1}]},"boundingBox":{"normalizedVertices":[{"x":0.17424242,"y":0.37179488},{"x":0.21212122,"y":0.37179488},{"x":0.21212122,"y":0.39957264},{"x":0.17424242,"y":0.39957264}]},"symbols":[{"text":"து","confidence":0.9770839},{"property":{"detectedBreak":{"type":"SPACE"}},"text":"ம்","confidence":0.97550225}],"confidence":0.9762931},{"property":{"detectedLanguages":[{"languageCode":"ta","confidence":1}]},"boundingBox":{"normalizedVertices":[{"x":0.23737374,"y":0.37179488},{"x":0.32828283,"y":0.37179488},{"x":0.32828283,"y":0.39957264},{"x":0.23737374,"y":0.39957264}]},"symbols":[{"text":"ஒ","confidence":0.9896947},{"text":"ன்றி","confidence":0.9945644},{"property":{"detectedBreak":{"type":"SPACE"}},"text":"ல்","confidence":0.9978838}],"confidence":0.99404764},{"property":{"detectedLanguages":[{"languageCode":"ta","confidence":1}]},"boundingBox":{"normalizedVertices":[{"x":0.34848484,"y":0.3696581},{"x":0.43939394,"y":0.3696581},{"x":0.43939394,"y":0.3974359},{"x":0.34848484,"y":0.39957264}]},"symbols":[{"text":"ஒ","confidence":0.99334633},{"text":"ன்ற","confidence":0.9923982},{"property":{"detectedBreak":{"type":"SPACE"}},"text":"ன்","confidence":0.9954849}],"confidence":0.9937431},{"property":{"detectedLanguages":[{"languageCode":"ta","confidence":1}]},"boundingBox":{"normalizedVertices":[{"x":0.4722222,"y":0.3696581},{"x":0.6969697,"y":0.36752138},{"x":0.69949496,"y":0.39529914},{"x":0.47474748,"y":0.3974359}]},"symbols":[{"text":"அ","confidence":0.9916954},{"text":"த்தி","confidence":0.9935793},{"text":"யா","confidence":0.9937068},{"text":"ச","confidence":0.9954583},{"text":"வ","confidence":0.9937926},{"text":"ச","confidence":0.98974776},{"text":"த்தா","confidence":0.98263323},{"property":{"detectedBreak":{"type":"SPACE"}},"text":"ல்","confidence":0.99357796}],"confidence":0.9917739},{"property":{"detectedLanguages":[{"languageCode":"ta","confidence":1}]},"boundingBox":{"normalizedVertices":[{"x":0.719697,"y":0.36752138},{"x":0.8333333,"y":0.36752138},{"x":0.8333333,"y":0.39529914},{"x":0.7222222,"y":0.39529914}]},"symbols":[{"text":"ஜ","confidence":0.9342092},{"text":"ட","confidence":0.99413073},{"text":"த்து","confidence":0.9869642},{"property":{"detectedBreak":{"type":"EOL_SURE_SPACE"}},"text":"வ","confidence":0.9909847}],"confidence":0.9765722},{"property":{"detectedLanguages":[{"languageCode":"ta","confidence":1}]},"boundingBox":{"normalizedVertices":[{"x":0.17929293,"y":0.4017094},{"x":0.21212122,"y":0.39957264},{"x":0.21212122,"y":0.42948717},{"x":0.17929293,"y":0.42948717}]},"symbols":[{"text":"மு","confidence":0.9443225},{"property":{"detectedBreak":{"type":"SPACE"}},"text":"ம்","confidence":0.9791629}],"confidence":0.9617427},{"property":{"detectedLanguages":[{"languageCode":"ta","confidence":1}]},"boundingBox":{"normalizedVertices":[{"x":0.22727273,"y":0.39957264},{"x":0.41414142,"y":0.39957264},{"x":0.41414142,"y":0.42735043},{"x":0.22727273,"y":0.42948717}]},"symbols":[{"text":"அ","confidence":0.9594846},{"text":"ஜ","confidence":0.9335763},{"text":"ட","confidence":0.98940456},{"text":"த்து","confidence":0.9935884},{"text":"வ","confidence":0.99463224},{"text":"மு","confidence":0.9955493},{"property":{"detectedBreak":{"type":"SPACE"}},"text":"ம்","confidence":0.9959332}],"confidence":0.9803098},{"property":{"detectedLanguages":[{"languageCode":"ta","confidence":1}]},"boundingBox":{"normalizedVertices":[{"x":0.42929292,"y":0.39957264},{"x":0.6111111,"y":0.3974359},{"x":0.6111111,"y":0.42521366},{"x":0.42929292,"y":0.42735043}]},"symbols":[{"text":"தோ","confidence":0.9819411},{"text":"ற்று","confidence":0.9825444},{"text":"கி","confidence":0.9935301},{"text":"ன்ற","confidence":0.98875004},{"text":"ன","confidence":0.9952131}],"confidence":0.98839575},{"property":{"detectedLanguages":[{"languageCode":"ta","confidence":1}]},"boundingBox":{"normalizedVertices":[{"x":0.61616164,"y":0.3974359},{"x":0.6237374,"y":0.3974359},{"x":0.6262626,"y":0.42521366},{"x":0.61616164,"y":0.42521366}]},"symbols":[{"property":{"detectedBreak":{"type":"SPACE"}},"text":".","confidence":0.9587945}],"confidence":0.9587945},{"property":{"detectedLanguages":[{"languageCode":"ta","confidence":1}]},"boundingBox":{"normalizedVertices":[{"x":0.74747473,"y":0.3974359},{"x":0.75757575,"y":0.3974359},{"x":0.75757575,"y":0.42521366},{"x":0.74747473,"y":0.42521366}]},"symbols":[{"text":"(","confidence":0.9399334}],"confidence":0.9399334},{"property":{"detectedLanguages":[{"languageCode":"ta","confidence":1}]},"boundingBox":{"normalizedVertices":[{"x":0.7626263,"y":0.3974359},{"x":0.77272725,"y":0.3974359},{"x":0.7752525,"y":0.42521366},{"x":0.7626263,"y":0.42521366}]},"symbols":[{"text":"எ","confidence":0.96881425}],"confidence":0.96881425},{"property":{"detectedLanguages":[{"languageCode":"ta","confidence":1}]},"boundingBox":{"normalizedVertices":[{"x":0.7752525,"y":0.3974359},{"x":0.7878788,"y":0.3974359},{"x":0.790404,"y":0.42521366},{"x":0.7752525,"y":0.42521366}]},"symbols":[{"text":"-","confidence":0.9795267}],"confidence":0.9795267},{"property":{"detectedLanguages":[{"languageCode":"ta","confidence":1}]},"boundingBox":{"normalizedVertices":[{"x":0.79545456,"y":0.3974359},{"x":0.81060606,"y":0.3974359},{"x":0.81060606,"y":0.42521366},{"x":0.7979798,"y":0.42521366}]},"symbols":[{"text":"று","confidence":0.9756385}],"confidence":0.9756385},{"property":{"detectedLanguages":[{"languageCode":"ta","confidence":1}]},"boundingBox":{"normalizedVertices":[{"x":0.81313133,"y":0.3974359},{"x":0.8207071,"y":0.3974359},{"x":0.82323235,"y":0.42307693},{"x":0.81313133,"y":0.42307693}]},"symbols":[{"text":".","confidence":0.75032395}],"confidence":0.75032395},{"property":{"detectedLanguages":[{"languageCode":"ta","confidence":1}]},"boundingBox":{"normalizedVertices":[{"x":0.82323235,"y":0.3974359},{"x":0.8333333,"y":0.3974359},{"x":0.8333333,"y":0.42307693},{"x":0.82575756,"y":0.42307693}]},"symbols":[{"property":{"detectedBreak":{"type":"LINE_BREAK"}},"text":")","confidence":0.87137306}],"confidence":0.87137306}],"confidence":0.97682506},{"boundingBox":{"normalizedVertices":[{"x":0.16414142,"y":0.43803418},{"x":0.8333333,"y":0.42735043},{"x":0.8358586,"y":0.61538464},{"x":0.16666667,"y":0.62606835}]},"words":[{"property":{"detectedLanguages":[{"languageCode":"ta","confidence":1}]},"boundingBox":{"normalizedVertices":[{"x":0.22474748,"y":0.43803418},{"x":0.37121212,"y":0.43589744},{"x":0.37373737,"y":0.4636752},{"x":0.22474748,"y":0.46581197}]},"symbols":[{"text":"சி","confidence":0.977775},{"text":"த்த","confidence":0.9793335},{"text":"த்தி","confidence":0.9871176},{"property":{"detectedBreak":{"type":"SPACE"}},"text":"ற்கு","confidence":0.9883952}],"confidence":0.9831553},{"property":{"detectedLanguages":[{"languageCode":"ta","confidence":1}]},"boundingBox":{"normalizedVertices":[{"x":0.3939394,"y":0.43589744},{"x":0.40151516,"y":0.43589744},{"x":0.40151516,"y":0.4636752},{"x":0.3939394,"y":0.4636752}]},"symbols":[{"text":"(","confidence":0.98454446}],"confidence":0.98454446},{"property":{"detectedLanguages":[{"languageCode":"ta","confidence":1}]},"boundingBox":{"normalizedVertices":[{"x":0.4040404,"y":0.43589744},{"x":0.5555556,"y":0.43376067},{"x":0.5555556,"y":0.46153846},{"x":0.4040404,"y":0.4636752}]},"symbols":[{"text":"வி","confidence":0.99399596},{"text":"ரு","confidence":0.99335307},{"text":"த்தி","confidence":0.9830732},{"text":"க","confidence":0.9925734},{"text":"ளு","confidence":0.9925107},{"text":"க்கு","confidence":0.98550344}],"confidence":0.9901683},{"property":{"detectedLanguages":[{"languageCode":"ta","confidence":1}]},"boundingBox":{"normalizedVertices":[{"x":0.56060606,"y":0.43376067},{"x":0.59343433,"y":0.43376067},{"x":0.59343433,"y":0.46153846},{"x":0.56060606,"y":0.46153846}]},"symbols":[{"property":{"detectedBreak":{"type":"SPACE"}},"text":")","confidence":0.9464871}],"confidence":0.9464871},{"property":{"detectedLanguages":[{"languageCode":"ta","confidence":1}]},"boundingBox":{"normalizedVertices":[{"x":0.6060606,"y":0.43376067},{"x":0.82323235,"y":0.43162394},{"x":0.82323235,"y":0.4594017},{"x":0.6060606,"y":0.46153846}]},"symbols":[{"text":"ஞா","confidence":0.9482777},{"text":"ன","confidence":0.99311286},{"text":"த்த","confidence":0.9909565},{"text":"ன்மை","confidence":0.9909731},{"text":"யு","confidence":0.9976453},{"text":"ம்","confidence":0.9983951}],"confidence":0.9865601},{"property":{"detectedLanguages":[{"languageCode":"ta","confidence":1}]},"boundingBox":{"normalizedVertices":[{"x":0.82828283,"y":0.43162394},{"x":0.8333333,"y":0.43162394},{"x":0.8333333,"y":0.4594017},{"x":0.82828283,"y":0.4594017}]},"symbols":[{"property":{"detectedBreak":{"type":"EOL_SURE_SPACE"}},"text":",","confidence":0.98676044}],"confidence":0.98676044},{"property":{"detectedLanguages":[{"languageCode":"ta","confidence":1}]},"boundingBox":{"normalizedVertices":[{"x":0.16919191,"y":0.4679487},{"x":0.3459596,"y":0.46581197},{"x":0.3459596,"y":0.49358973},{"x":0.16919191,"y":0.4957265}]},"symbols":[{"text":"ஜீ","confidence":0.9676035},{"text":"வா","confidence":0.9857646},{"text":"த்மா","confidence":0.99231344},{"text":"வி","confidence":0.99616694},{"property":{"detectedBreak":{"type":"SPACE"}},"text":"ற்கு","confidence":0.9913792}],"confidence":0.9866455},{"property":{"detectedLanguages":[{"languageCode":"ta","confidence":1}]},"boundingBox":{"normalizedVertices":[{"x":0.3560606,"y":0.46581197},{"x":0.5479798,"y":0.46581197},{"x":0.5479798,"y":0.491453},{"x":0.3560606,"y":0.49358973}]},"symbols":[{"text":"ஜ","confidence":0.9935244},{"text":"ட","confidence":0.992139},{"text":"த்த","confidence":0.98392713},{"text":"ன்மை","confidence":0.9730714},{"text":"யு","confidence":0.99755967},{"property":{"detectedBreak":{"type":"SPACE"}},"text":"ம்","confidence":0.997582}],"confidence":0.9896339},{"property":{"detectedLanguages":[{"languageCode":"ta","confidence":1}]},"boundingBox":{"normalizedVertices":[{"x":0.56060606,"y":0.46581197},{"x":0.74242425,"y":0.4636752},{"x":0.74242425,"y":0.491453},{"x":0.56060606,"y":0.491453}]},"symbols":[{"text":"தோ","confidence":0.98976153},{"text":"ற்று","confidence":0.9899671},{"text":"கி","confidence":0.990637},{"text":"ன்ற","confidence":0.992224},{"text":"ன","confidence":0.99656755}],"confidence":0.9918314},{"property":{"detectedLanguages":[{"languageCode":"ta","confidence":1}]},"boundingBox":{"normalizedVertices":[{"x":0.74747473,"y":0.4636752},{"x":0.7550505,"y":0.4636752},{"x":0.75757575,"y":0.491453},{"x":0.74747473,"y":0.491453}]},"symbols":[{"property":{"detectedBreak":{"type":"SPACE"}},"text":".","confidence":0.986719}],"confidence":0.986719},{"property":{"detectedLanguages":[{"languageCode":"ta","confidence":1}]},"boundingBox":{"normalizedVertices":[{"x":0.7878788,"y":0.4636752},{"x":0.8308081,"y":0.4636752},{"x":0.8308081,"y":0.48931623},{"x":0.7878788,"y":0.48931623}]},"symbols":[{"text":"இ","confidence":0.98881555},{"property":{"detectedBreak":{"type":"EOL_SURE_SPACE"}},"text":"த","confidence":0.9534145}],"confidence":0.971115},{"property":{"detectedLanguages":[{"languageCode":"ta","confidence":1}]},"boundingBox":{"normalizedVertices":[{"x":0.16919191,"y":0.5},{"x":0.2651515,"y":0.49786323},{"x":0.2651515,"y":0.5277778},{"x":0.16919191,"y":0.52991456}]},"symbols":[{"text":"னா","confidence":0.8068054},{"text":"ற்றா","confidence":0.9571273},{"property":{"detectedBreak":{"type":"SPACE"}},"text":"ன்","confidence":0.99578667}],"confidence":0.91990644},{"property":{"detectedLanguages":[{"languageCode":"ta","confidence":1}]},"boundingBox":{"normalizedVertices":[{"x":0.2777778,"y":0.49786323},{"x":0.41919193,"y":0.4957265},{"x":0.41919193,"y":0.5277778},{"x":0.2777778,"y":0.5277778}]},"symbols":[{"text":"ஞா","confidence":0.98848224},{"text":"னா","confidence":0.9602537},{"text":"சி","confidence":0.9725922},{"text":"ர","confidence":0.97494847},{"text":"ய","confidence":0.96428174},{"property":{"detectedBreak":{"type":"SPACE"}},"text":"ம்","confidence":0.98728675}],"confidence":0.97464085},{"property":{"detectedLanguages":[{"languageCode":"ta","confidence":1}]},"boundingBox":{"normalizedVertices":[{"x":0.42676768,"y":0.4957265},{"x":0.5,"y":0.4957265},{"x":0.5,"y":0.525641},{"x":0.42676768,"y":0.525641}]},"symbols":[{"text":"ஆ","confidence":0.98195416},{"property":{"detectedBreak":{"type":"SPACE"}},"text":"த்மா","confidence":0.96777976}],"confidence":0.974867},{"property":{"detectedLanguages":[{"languageCode":"ta","confidence":1}]},"boundingBox":{"normalizedVertices":[{"x":0.510101,"y":0.4957265},{"x":0.60353535,"y":0.49358973},{"x":0.60353535,"y":0.52350426},{"x":0.510101,"y":0.525641}]},"symbols":[{"text":"வெ","confidence":0.98305},{"property":{"detectedBreak":{"type":"SPACE"}},"text":"ன்று","confidence":0.98010945}],"confidence":0.9815797},{"property":{"detectedLanguages":[{"languageCode":"ta","confidence":1}]},"boundingBox":{"normalizedVertices":[{"x":0.6136364,"y":0.49358973},{"x":0.7222222,"y":0.491453},{"x":0.7222222,"y":0.52350426},{"x":0.6136364,"y":0.52350426}]},"symbols":[{"text":"தா","confidence":0.9923778},{"text":"ர்க்கி","confidence":0.93986005},{"text":"க","confidence":0.9732084},{"property":{"detectedBreak":{"type":"SPACE"}},"text":"ர்","confidence":0.94553244}],"confidence":0.9627447},{"property":{"detectedLanguages":[{"languageCode":"ta","confidence":1}]},"boundingBox":{"normalizedVertices":[{"x":0.72727275,"y":0.491453},{"x":0.8308081,"y":0.491453},{"x":0.8308081,"y":0.52136755},{"x":0.72727275,"y":0.52136755}]},"symbols":[{"text":"வி","confidence":0.9819939},{"text":"ய","confidence":0.9861696},{"text":"வ","confidence":0.9968945},{"text":"கா","confidence":0.9940535},{"property":{"detectedBreak":{"type":"EOL_SURE_SPACE"}},"text":"ர","confidence":0.98893934}],"confidence":0.98961014},{"property":{"detectedLanguages":[{"languageCode":"ta","confidence":1}]},"boundingBox":{"normalizedVertices":[{"x":0.18181819,"y":0.53205127},{"x":0.21464646,"y":0.52991456},{"x":0.21464646,"y":0.5576923},{"x":0.18181819,"y":0.55982906}]},"symbols":[{"text":"மு","confidence":0.95972115},{"text":"ம்","confidence":0.9812681}],"confidence":0.9704946},{"property":{"detectedLanguages":[{"languageCode":"ta","confidence":1}]},"boundingBox":{"normalizedVertices":[{"x":0.21717171,"y":0.52991456},{"x":0.22474748,"y":0.52991456},{"x":0.22727273,"y":0.5576923},{"x":0.21717171,"y":0.5576923}]},"symbols":[{"property":{"detectedBreak":{"type":"SPACE"}},"text":",","confidence":0.9584798}],"confidence":0.9584798},{"property":{"detectedLanguages":[{"languageCode":"ta","confidence":1}]},"boundingBox":{"normalizedVertices":[{"x":0.25,"y":0.52991456},{"x":0.48737374,"y":0.525641},{"x":0.48737374,"y":0.5555556},{"x":0.25,"y":0.5576923}]},"symbols":[{"text":"ஜீ","confidence":0.96896505},{"text":"வா","confidence":0.9823603},{"text":"த்மா","confidence":0.9922476},{"text":"வி","confidence":0.99631065},{"text":"னி","confidence":0.99788374},{"text":"ட","confidence":0.9982578},{"property":{"detectedBreak":{"type":"SPACE"}},"text":"த்து","confidence":0.9953216}],"confidence":0.9901924},{"property":{"detectedLanguages":[{"languageCode":"ta","confidence":1}]},"boundingBox":{"normalizedVertices":[{"x":0.5252525,"y":0.525641},{"x":0.6919192,"y":0.52350426},{"x":0.6919192,"y":0.55128205},{"x":0.5252525,"y":0.5555556}]},"symbols":[{"text":"அ","confidence":0.9962204},{"text":"றி","confidence":0.9956773},{"text":"ஞ","confidence":0.99409807},{"text":"ர்க","confidence":0.99173486},{"text":"ளா","confidence":0.99400544},{"property":{"detectedBreak":{"type":"SPACE"}},"text":"ல்","confidence":0.99294513}],"confidence":0.99411356},{"property":{"detectedLanguages":[{"languageCode":"ta","confidence":1}]},"boundingBox":{"normalizedVertices":[{"x":0.72727275,"y":0.52991456},{"x":0.8333333,"y":0.525641},{"x":0.8333333,"y":0.5491453},{"x":0.72979796,"y":0.5534188}]},"symbols":[{"text":"ஜ","confidence":0.96258074},{"text":"டா","confidence":0.95967335},{"property":{"detectedBreak":{"type":"EOL_SURE_SPACE"}},"text":"த்மா","confidence":0.9555646}],"confidence":0.9592729},{"property":{"detectedLanguages":[{"languageCode":"ta","confidence":1}]},"boundingBox":{"normalizedVertices":[{"x":0.16919191,"y":0.55982906},{"x":0.2550505,"y":0.55982906},{"x":0.2550505,"y":0.58760685},{"x":0.17171717,"y":0.58760685}]},"symbols":[{"text":"வெ","confidence":0.96715224},{"property":{"detectedBreak":{"type":"SPACE"}},"text":"ன்று","confidence":0.9850093}],"confidence":0.9760808},{"property":{"detectedLanguages":[{"languageCode":"ta","confidence":1}]},"boundingBox":{"normalizedVertices":[{"x":0.270202,"y":0.55982906},{"x":0.5050505,"y":0.5576923},{"x":0.5050505,"y":0.5854701},{"x":0.270202,"y":0.5854701}]},"symbols":[{"text":"சொ","confidence":0.9816933},{"text":"ல்ல","confidence":0.98718613},{"text":"ப்ப","confidence":0.97481966},{"text":"டு","confidence":0.9919225},{"text":"கி","confidence":0.9931506},{"text":"ன்ற","confidence":0.99113965},{"property":{"detectedBreak":{"type":"SPACE"}},"text":"து","confidence":0.99376607}],"confidence":0.9876683},{"property":{"detectedLanguages":[{"languageCode":"ta","confidence":1}]},"boundingBox":{"normalizedVertices":[{"x":0.52020204,"y":0.5576923},{"x":0.5858586,"y":0.5576923},{"x":0.5858586,"y":0.5833333},{"x":0.52272725,"y":0.5854701}]},"symbols":[{"text":"எ","confidence":0.99026597},{"property":{"detectedBreak":{"type":"SPACE"}},"text":"ன்று","confidence":0.9890705}],"confidence":0.98966825},{"property":{"detectedLanguages":[{"languageCode":"ta","confidence":1}]},"boundingBox":{"normalizedVertices":[{"x":0.6262626,"y":0.5576923},{"x":0.7348485,"y":0.5555556},{"x":0.7373737,"y":0.5833333},{"x":0.6262626,"y":0.5833333}]},"symbols":[{"text":"ஸ்மா","confidence":0.9678938},{"text":"ர்த்த","confidence":0.9520168},{"property":{"detectedBreak":{"type":"SPACE"}},"text":"ர்","confidence":0.9690223}],"confidence":0.9629776},{"property":{"detectedLanguages":[{"languageCode":"ta","confidence":1}]},"boundingBox":{"normalizedVertices":[{"x":0.7449495,"y":0.5555556},{"x":0.8333333,"y":0.5555556},{"x":0.8333333,"y":0.5833333},{"x":0.7449495,"y":0.5833333}]},"symbols":[{"text":"வி","confidence":0.9832304},{"text":"ய","confidence":0.9702237},{"text":"வ","confidence":0.9910607},{"property":{"detectedBreak":{"type":"EOL_SURE_SPACE"}},"text":"கா","confidence":0.9807075}],"confidence":0.9813056},{"property":{"detectedLanguages":[{"languageCode":"ta","confidence":1}]},"boundingBox":{"normalizedVertices":[{"x":0.16666667,"y":0.5940171},{"x":0.20707071,"y":0.5918803},{"x":0.20959596,"y":0.62393165},{"x":0.16919191,"y":0.62606835}]},"symbols":[{"text":"ர","confidence":0.9518495},{"property":{"detectedBreak":{"type":"SPACE"}},"text":"மு","confidence":0.8541098}],"confidence":0.9029797},{"property":{"detectedLanguages":[{"languageCode":"ta","confidence":1}]},"boundingBox":{"normalizedVertices":[{"x":0.22979797,"y":0.5918803},{"x":0.27272728,"y":0.5918803},{"x":0.27525252,"y":0.6217949},{"x":0.23232323,"y":0.62393165}]},"symbols":[{"text":"மு","confidence":0.8783147},{"property":{"detectedBreak":{"type":"SPACE"}},"text":"ள","confidence":0.96934175}],"confidence":0.92382824},{"property":{"detectedLanguages":[{"languageCode":"ta","confidence":1}]},"boundingBox":{"normalizedVertices":[{"x":0.28030303,"y":0.5897436},{"x":0.39646465,"y":0.5854701},{"x":0.39646465,"y":0.61752135},{"x":0.28030303,"y":0.6217949}]},"symbols":[{"text":"தா","confidence":0.9800496},{"text":"கி","confidence":0.9893685},{"text":"ன்ற","confidence":0.9878314},{"text":"து","confidence":0.99149394}],"confidence":0.98718584},{"property":{"detectedLanguages":[{"languageCode":"ta","confidence":1}]},"boundingBox":{"normalizedVertices":[{"x":0.3989899,"y":0.5854701},{"x":0.40656567,"y":0.5854701},{"x":0.4090909,"y":0.61752135},{"x":0.40151516,"y":0.61752135}]},"symbols":[{"property":{"detectedBreak":{"type":"LINE_BREAK"}},"text":".","confidence":0.94110525}],"confidence":0.94110525}],"confidence":0.9779766}],"blockType":"TEXT","confidence":0.96447265},{"boundingBox":{"normalizedVertices":[{"x":0.7777778,"y":0.5854701},{"x":0.8358586,"y":0.5854701},{"x":0.8358586,"y":0.6132479},{"x":0.7777778,"y":0.6111111}]},"paragraphs":[{"boundingBox":{"normalizedVertices":[{"x":0.7777778,"y":0.5854701},{"x":0.8358586,"y":0.5854701},{"x":0.8358586,"y":0.6132479},{"x":0.7777778,"y":0.6111111}]},"words":[{"boundingBox":{"normalizedVertices":[{"x":0.7777778,"y":0.5854701},{"x":0.790404,"y":0.5854701},{"x":0.790404,"y":0.6111111},{"x":0.7777778,"y":0.6111111}]},"symbols":[{"text":"(","confidence":0.9335492}],"confidence":0.9335492},{"boundingBox":{"normalizedVertices":[{"x":0.7929293,"y":0.5854701},{"x":0.82323235,"y":0.5854701},{"x":0.82323235,"y":0.6111111},{"x":0.7929293,"y":0.6111111}]},"symbols":[{"text":"ச","confidence":0.9219827},{"text":"க","confidence":0.98719305}],"confidence":0.9545879},{"boundingBox":{"normalizedVertices":[{"x":0.82575756,"y":0.5854701},{"x":0.8358586,"y":0.5854701},{"x":0.8358586,"y":0.6111111},{"x":0.82575756,"y":0.6111111}]},"symbols":[{"property":{"detectedBreak":{"type":"LINE_BREAK"}},"text":")","confidence":0.9682086}],"confidence":0.9682086}],"confidence":0.9527334}],"blockType":"TEXT","confidence":0.9527334},{"boundingBox":{"normalizedVertices":[{"x":0.16919191,"y":0.64102566},{"x":0.84090906,"y":0.63461536},{"x":0.8459596,"y":0.82905984},{"x":0.17171717,"y":0.8354701}]},"paragraphs":[{"boundingBox":{"normalizedVertices":[{"x":0.16919191,"y":0.64102566},{"x":0.82575756,"y":0.63461536},{"x":0.82828283,"y":0.7051282},{"x":0.17171717,"y":0.71153843}]},"words":[{"property":{"detectedLanguages":[{"languageCode":"sa","confidence":1}]},"boundingBox":{"normalizedVertices":[{"x":0.16919191,"y":0.64102566},{"x":0.21717171,"y":0.6388889},{"x":0.21717171,"y":0.6730769},{"x":0.17171717,"y":0.6730769}]},"symbols":[{"text":"गु","confidence":0.64746165},{"property":{"detectedBreak":{"type":"SPACE"}},"text":"रोः","confidence":0.5030115}],"confidence":0.57523656},{"property":{"detectedLanguages":[{"languageCode":"sa","confidence":1}]},"boundingBox":{"normalizedVertices":[{"x":0.22979797,"y":0.6388889},{"x":0.3409091,"y":0.6388889},{"x":0.3409091,"y":0.6730769},{"x":0.22979797,"y":0.6730769}]},"symbols":[{"text":"स","confidence":0.9265687},{"text":"का","confidence":0.9052205},{"text":"शा","confidence":0.9431712},{"text":"द","confidence":0.970743},{"property":{"detectedBreak":{"type":"SPACE"}},"text":"पि","confidence":0.9154177}],"confidence":0.9322242},{"property":{"detectedLanguages":[{"languageCode":"sa","confidence":1}]},"boundingBox":{"normalizedVertices":[{"x":0.3510101,"y":0.6388889},{"x":0.46212122,"y":0.6388889},{"x":0.46464646,"y":0.67094016},{"x":0.3510101,"y":0.6730769}]},"symbols":[{"text":"वे","confidence":0.86512786},{"text":"द","confidence":0.9411042},{"text":"वा","confidence":0.8784919},{"text":"क्य","confidence":0.94032633},{"property":{"detectedBreak":{"type":"SPACE"}},"text":"तः","confidence":0.86920685}],"confidence":0.8988514},{"property":{"detectedLanguages":[{"languageCode":"sa","confidence":1}]},"boundingBox":{"normalizedVertices":[{"x":0.47474748,"y":0.6388889},{"x":0.64646465,"y":0.6367521},{"x":0.64646465,"y":0.67094016},{"x":0.47474748,"y":0.67094016}]},"symbols":[{"text":"स","confidence":0.95684},{"text":"ञ्जा","confidence":0.80974436},{"text":"त","confidence":0.97038203},{"text":"वि","confidence":0.96466714},{"text":"द्या","confidence":0.9430721},{"text":"नु","confidence":0.96626383},{"text":"भ","confidence":0.9726237},{"property":{"detectedBreak":{"type":"SPACE"}},"text":"वो","confidence":0.92847353}],"confidence":0.93900836},{"property":{"detectedLanguages":[{"languageCode":"sa","confidence":1}]},"boundingBox":{"normalizedVertices":[{"x":0.65656567,"y":0.6367521},{"x":0.72727275,"y":0.6367521},{"x":0.72727275,"y":0.67094016},{"x":0.65656567,"y":0.67094016}]},"symbols":[{"text":"नि","confidence":0.9144123},{"text":"री","confidence":0.96913505},{"property":{"detectedBreak":{"type":"SPACE"}},"text":"क्ष्य","confidence":0.92807823}],"confidence":0.93720853},{"property":{"detectedLanguages":[{"languageCode":"sa","confidence":1}]},"boundingBox":{"normalizedVertices":[{"x":0.7348485,"y":0.6367521},{"x":0.77272725,"y":0.6367521},{"x":0.7752525,"y":0.6688034},{"x":0.7373737,"y":0.6688034}]},"symbols":[{"text":"त","confidence":0.948249},{"property":{"detectedBreak":{"type":"SPACE"}},"text":"म्","confidence":0.87761843}],"confidence":0.9129337},{"property":{"detectedLanguages":[{"languageCode":"sa","confidence":1}]},"boundingBox":{"normalizedVertices":[{"x":0.78535354,"y":0.6367521},{"x":0.7878788,"y":0.6367521},{"x":0.7878788,"y":0.6688034},{"x":0.78535354,"y":0.6688034}]},"symbols":[{"property":{"detectedBreak":{"type":"EOL_SURE_SPACE"}},"text":"।","confidence":0.82089114}],"confidence":0.82089114},{"property":{"detectedLanguages":[{"languageCode":"sa","confidence":1}]},"boundingBox":{"normalizedVertices":[{"x":0.17171717,"y":0.68162394},{"x":0.44949496,"y":0.6773504},{"x":0.44949496,"y":0.70726496},{"x":0.17171717,"y":0.71153843}]},"symbols":[{"text":"स्वा","confidence":0.91190284},{"text":"त्मा","confidence":0.9130587},{"text":"न","confidence":0.97769564},{"text":"मा","confidence":0.9504119},{"text":"त्म","confidence":0.9553329},{"text":"स्थ","confidence":0.93785506},{"text":"मु","confidence":0.9338312},{"text":"पा","confidence":0.9487352},{"text":"धि","confidence":0.95097286},{"text":"व","confidence":0.9680115},{"text":"र्जि","confidence":0.8906261},{"property":{"detectedBreak":{"type":"SPACE"}},"text":"तं","confidence":0.8941858}],"confidence":0.9360516},{"property":{"detectedLanguages":[{"languageCode":"sa","confidence":1}]},"boundingBox":{"normalizedVertices":[{"x":0.45959595,"y":0.6773504},{"x":0.5555556,"y":0.6773504},{"x":0.5580808,"y":0.70726496},{"x":0.46212122,"y":0.70726496}]},"symbols":[{"text":"त्य","confidence":0.92819524},{"text":"जे","confidence":0.9545849},{"text":"द","confidence":0.9780411},{"text":"शे","confidence":0.94956183},{"property":{"detectedBreak":{"type":"SPACE"}},"text":"षं","confidence":0.7861961}],"confidence":0.9193158},{"property":{"detectedLanguages":[{"languageCode":"sa","confidence":1}]},"boundingBox":{"normalizedVertices":[{"x":0.56565654,"y":0.6752137},{"x":0.7348485,"y":0.6752137},{"x":0.7348485,"y":0.7051282},{"x":0.5681818,"y":0.70726496}]},"symbols":[{"text":"ज","confidence":0.96094155},{"text":"ड","confidence":0.9505173},{"text":"मा","confidence":0.9424498},{"text":"त्म","confidence":0.9504633},{"text":"गो","confidence":0.9433176},{"text":"च","confidence":0.9678051},{"text":"र","confidence":0.96245205},{"property":{"detectedBreak":{"type":"SPACE"}},"text":"म्","confidence":0.89744455}],"confidence":0.9469239},{"property":{"detectedLanguages":[{"languageCode":"sa","confidence":1}]},"boundingBox":{"normalizedVertices":[{"x":0.74747473,"y":0.6752137},{"x":0.75252527,"y":0.6752137},{"x":0.75252527,"y":0.7051282},{"x":0.74747473,"y":0.7051282}]},"symbols":[{"property":{"detectedBreak":{"type":"SPACE"}},"text":"॥","confidence":0.7476992}],"confidence":0.7476992},{"property":{"detectedLanguages":[{"languageCode":"sa","confidence":1}]},"boundingBox":{"normalizedVertices":[{"x":0.7752525,"y":0.6730769},{"x":0.81060606,"y":0.6730769},{"x":0.81060606,"y":0.7029914},{"x":0.7752525,"y":0.7051282}]},"symbols":[{"text":"४","confidence":0.86690545},{"property":{"detectedBreak":{"type":"SPACE"}},"text":"२","confidence":0.8833268}],"confidence":0.8751161},{"property":{"detectedLanguages":[{"languageCode":"sa","confidence":1}]},"boundingBox":{"normalizedVertices":[{"x":0.82323235,"y":0.6730769},{"x":0.82828283,"y":0.6730769},{"x":0.82828283,"y":0.7029914},{"x":0.82323235,"y":0.7029914}]},"symbols":[{"property":{"detectedBreak":{"type":"LINE_BREAK"}},"text":"॥","confidence":0.7876876}],"confidence":0.7876876}],"confidence":0.908482},{"boundingBox":{"normalizedVertices":[{"x":0.17171717,"y":0.72863245},{"x":0.84343433,"y":0.7222222},{"x":0.8459596,"y":0.82905984},{"x":0.17424242,"y":0.8354701}]},"words":[{"property":{"detectedLanguages":[{"languageCode":"ta","confidence":1}]},"boundingBox":{"normalizedVertices":[{"x":0.22474748,"y":0.7307692},{"x":0.23737374,"y":0.7307692},{"x":0.23737374,"y":0.75641024},{"x":0.22474748,"y":0.75641024}]},"symbols":[{"property":{"detectedBreak":{"type":"SPACE"}},"text":"*","confidence":0.90538013}],"confidence":0.90538013},{"property":{"detectedLanguages":[{"languageCode":"ta","confidence":1}]},"boundingBox":{"normalizedVertices":[{"x":0.24747474,"y":0.7307692},{"x":0.33333334,"y":0.72863245},{"x":0.33333334,"y":0.75641024},{"x":0.25,"y":0.75641024}]},"symbols":[{"text":"அ","confidence":0.99172604},{"text":"ன","confidence":0.9941602},{"text":"லி","confidence":0.994138},{"property":{"detectedBreak":{"type":"SPACE"}},"text":"ல்","confidence":0.995651}],"confidence":0.9939188},{"property":{"detectedLanguages":[{"languageCode":"ta","confidence":1}]},"boundingBox":{"normalizedVertices":[{"x":0.34343433,"y":0.72863245},{"x":0.41414142,"y":0.72863245},{"x":0.41414142,"y":0.75427353},{"x":0.34343433,"y":0.75427353}]},"symbols":[{"text":"இ","confidence":0.99846643},{"text":"ரு","confidence":0.99568504},{"property":{"detectedBreak":{"type":"SPACE"}},"text":"ம்பு","confidence":0.97953683}],"confidence":0.9912294},{"property":{"detectedLanguages":[{"languageCode":"ta","confidence":1}]},"boundingBox":{"normalizedVertices":[{"x":0.42676768,"y":0.72649574},{"x":0.6363636,"y":0.724359},{"x":0.6363636,"y":0.75213677},{"x":0.42929292,"y":0.75427353}]},"symbols":[{"text":"கா","confidence":0.9932274},{"text":"ய்ச்ச","confidence":0.97169065},{"text":"ப்ப","confidence":0.9800117},{"text":"ட்ட","confidence":0.98717755},{"text":"போ","confidence":0.9847292},{"property":{"detectedBreak":{"type":"SPACE"}},"text":"து","confidence":0.99664634}],"confidence":0.98558044},{"property":{"detectedLanguages":[{"languageCode":"ta","confidence":1}]},"boundingBox":{"normalizedVertices":[{"x":0.6540404,"y":0.724359},{"x":0.7676768,"y":0.724359},{"x":0.7676768,"y":0.75},{"x":0.6540404,"y":0.75213677}]},"symbols":[{"text":"அ","confidence":0.9917031},{"text":"க்கி","confidence":0.9601497},{"text":"னி","confidence":0.99346244},{"text":"யி","confidence":0.99892795},{"property":{"detectedBreak":{"type":"SPACE"}},"text":"ன்","confidence":0.99896175}],"confidence":0.98864096},{"property":{"detectedLanguages":[{"languageCode":"ta","confidence":1}]},"boundingBox":{"normalizedVertices":[{"x":0.7929293,"y":0.724359},{"x":0.83838385,"y":0.7222222},{"x":0.83838385,"y":0.75},{"x":0.7929293,"y":0.75}]},"symbols":[{"text":"எ","confidence":0.9945888},{"text":"ரி","confidence":0.9951663},{"property":{"detectedBreak":{"type":"EOL_SURE_SPACE"}},"text":"க்","confidence":0.98753846}],"confidence":0.99243116},{"property":{"detectedLanguages":[{"languageCode":"ta","confidence":1}]},"boundingBox":{"normalizedVertices":[{"x":0.17171717,"y":0.75641024},{"x":0.28030303,"y":0.75641024},{"x":0.28030303,"y":0.78418803},{"x":0.17424242,"y":0.78418803}]},"symbols":[{"text":"கு","confidence":0.9807789},{"text":"ந்த","confidence":0.9838684},{"property":{"detectedBreak":{"type":"SPACE"}},"text":"ன்மை","confidence":0.97998875}],"confidence":0.9815453},{"property":{"detectedLanguages":[{"languageCode":"ta","confidence":1}]},"boundingBox":{"normalizedVertices":[{"x":0.29040405,"y":0.75641024},{"x":0.40151516,"y":0.75427353},{"x":0.40151516,"y":0.78205127},{"x":0.29040405,"y":0.78418803}]},"symbols":[{"text":"இ","confidence":0.99689007},{"text":"ரு","confidence":0.9901272},{"text":"ம்பி","confidence":0.974752},{"text":"லு","confidence":0.9752834},{"text":"ம்","confidence":0.9905719}],"confidence":0.9855249},{"property":{"detectedLanguages":[{"languageCode":"ta","confidence":1}]},"boundingBox":{"normalizedVertices":[{"x":0.4040404,"y":0.75427353},{"x":0.4090909,"y":0.75427353},{"x":0.4090909,"y":0.78205127},{"x":0.4040404,"y":0.78205127}]},"symbols":[{"property":{"detectedBreak":{"type":"SPACE"}},"text":",","confidence":0.9848376}],"confidence":0.9848376},{"property":{"detectedLanguages":[{"languageCode":"ta","confidence":1}]},"boundingBox":{"normalizedVertices":[{"x":0.42171717,"y":0.75427353},{"x":0.5151515,"y":0.75427353},{"x":0.5151515,"y":0.78205127},{"x":0.42171717,"y":0.78205127}]},"symbols":[{"text":"இ","confidence":0.9920448},{"text":"ரு","confidence":0.98952687},{"text":"ம்பி","confidence":0.98638827},{"property":{"detectedBreak":{"type":"SPACE"}},"text":"ன்","confidence":0.9957066}],"confidence":0.9909166},{"property":{"detectedLanguages":[{"languageCode":"ta","confidence":1}]},"boundingBox":{"normalizedVertices":[{"x":0.5252525,"y":0.75427353},{"x":0.5959596,"y":0.75213677},{"x":0.5959596,"y":0.77991456},{"x":0.5252525,"y":0.78205127}]},"symbols":[{"text":"உ","confidence":0.9950029},{"text":"ரு","confidence":0.9853336},{"property":{"detectedBreak":{"type":"SPACE"}},"text":"ட்சி","confidence":0.9621925}],"confidence":0.980843},{"property":{"detectedLanguages":[{"languageCode":"ta","confidence":1}]},"boundingBox":{"normalizedVertices":[{"x":0.6136364,"y":0.75213677},{"x":0.7676768,"y":0.75},{"x":0.7676768,"y":0.7777778},{"x":0.6136364,"y":0.77991456}]},"symbols":[{"text":"நீ","confidence":0.9573843},{"text":"ட்சி","confidence":0.924864},{"text":"மு","confidence":0.9695751},{"text":"த","confidence":0.978997},{"text":"லி","confidence":0.9881937},{"text":"ய","confidence":0.9965043},{"property":{"detectedBreak":{"type":"SPACE"}},"text":"ன","confidence":0.9967014}],"confidence":0.9731743},{"property":{"detectedLanguages":[{"languageCode":"ta","confidence":1}]},"boundingBox":{"normalizedVertices":[{"x":0.78535354,"y":0.75},{"x":0.83838385,"y":0.75},{"x":0.83838385,"y":0.7777778},{"x":0.78535354,"y":0.7777778}]},"symbols":[{"text":"அ","confidence":0.9939247},{"property":{"detectedBreak":{"type":"EOL_SURE_SPACE"}},"text":"க்கி","confidence":0.97501516}],"confidence":0.9844699},{"property":{"detectedLanguages":[{"languageCode":"ta","confidence":1}]},"boundingBox":{"normalizedVertices":[{"x":0.17171717,"y":0.78205127},{"x":0.2550505,"y":0.77991456},{"x":0.25757575,"y":0.8076923},{"x":0.17424242,"y":0.8076923}]},"symbols":[{"text":"னி","confidence":0.81377894},{"text":"யி","confidence":0.97256005},{"text":"லு","confidence":0.9886449},{"property":{"detectedBreak":{"type":"SPACE"}},"text":"ம்","confidence":0.99614227}],"confidence":0.94278157},{"property":{"detectedLanguages":[{"languageCode":"ta","confidence":1}]},"boundingBox":{"normalizedVertices":[{"x":0.26262626,"y":0.77991456},{"x":0.40656567,"y":0.77991456},{"x":0.4090909,"y":0.8076923},{"x":0.26262626,"y":0.8076923}]},"symbols":[{"text":"கா","confidence":0.9937499},{"text":"ண","confidence":0.99598354},{"text":"ப்ப","confidence":0.9930125},{"text":"டு","confidence":0.9946938},{"text":"வ","confidence":0.9959987},{"property":{"detectedBreak":{"type":"SPACE"}},"text":"து","confidence":0.9910962}],"confidence":0.9940891},{"property":{"detectedLanguages":[{"languageCode":"ta","confidence":1}]},"boundingBox":{"normalizedVertices":[{"x":0.41161618,"y":0.77991456},{"x":0.4722222,"y":0.77991456},{"x":0.4722222,"y":0.8055556},{"x":0.41161618,"y":0.8076923}]},"symbols":[{"text":"போ","confidence":0.95783013},{"text":"ல","confidence":0.9845573}],"confidence":0.9711937},{"property":{"detectedLanguages":[{"languageCode":"ta","confidence":1}]},"boundingBox":{"normalizedVertices":[{"x":0.47474748,"y":0.77991456},{"x":0.48232323,"y":0.77991456},{"x":0.48232323,"y":0.8055556},{"x":0.47474748,"y":0.8055556}]},"symbols":[{"property":{"detectedBreak":{"type":"SPACE"}},"text":",","confidence":0.9790639}],"confidence":0.9790639},{"property":{"detectedLanguages":[{"languageCode":"ta","confidence":1}]},"boundingBox":{"normalizedVertices":[{"x":0.4949495,"y":0.77991456},{"x":0.57323235,"y":0.7777778},{"x":0.57323235,"y":0.8055556},{"x":0.49747476,"y":0.8055556}]},"symbols":[{"text":"சி","confidence":0.9943974},{"text":"த்தி","confidence":0.9933975},{"property":{"detectedBreak":{"type":"SPACE"}},"text":"ன்","confidence":0.99404377}],"confidence":0.9939462},{"property":{"detectedLanguages":[{"languageCode":"ta","confidence":1}]},"boundingBox":{"normalizedVertices":[{"x":0.58838385,"y":0.7777778},{"x":0.74242425,"y":0.7777778},{"x":0.74242425,"y":0.8034188},{"x":0.58838385,"y":0.8055556}]},"symbols":[{"text":"ஞா","confidence":0.9735492},{"text":"ன","confidence":0.99714524},{"text":"த்த","confidence":0.9907752},{"property":{"detectedBreak":{"type":"SPACE"}},"text":"ன்மை","confidence":0.9795605}],"confidence":0.9852575},{"property":{"detectedLanguages":[{"languageCode":"ta","confidence":1}]},"boundingBox":{"normalizedVertices":[{"x":0.7550505,"y":0.7777778},{"x":0.83838385,"y":0.775641},{"x":0.83838385,"y":0.8034188},{"x":0.7550505,"y":0.8034188}]},"symbols":[{"text":"சி","confidence":0.99643767},{"text":"த்த","confidence":0.986311},{"property":{"detectedBreak":{"type":"EOL_SURE_SPACE"}},"text":"த்தி","confidence":0.98965263}],"confidence":0.99080044},{"property":{"detectedLanguages":[{"languageCode":"ta","confidence":1}]},"boundingBox":{"normalizedVertices":[{"x":0.17424242,"y":0.8119658},{"x":0.21464646,"y":0.80982906},{"x":0.21464646,"y":0.8354701},{"x":0.17424242,"y":0.8354701}]},"symbols":[{"text":"லு","confidence":0.9717378},{"text":"ம்","confidence":0.9807751}],"confidence":0.9762565},{"property":{"detectedLanguages":[{"languageCode":"ta","confidence":1}]},"boundingBox":{"normalizedVertices":[{"x":0.21464646,"y":0.80982906},{"x":0.22222222,"y":0.80982906},{"x":0.22222222,"y":0.8354701},{"x":0.21464646,"y":0.8354701}]},"symbols":[{"property":{"detectedBreak":{"type":"SPACE"}},"text":",","confidence":0.9785345}],"confidence":0.9785345},{"property":{"detectedLanguages":[{"languageCode":"ta","confidence":1}]},"boundingBox":{"normalizedVertices":[{"x":0.22727273,"y":0.80982906},{"x":0.33585858,"y":0.80982906},{"x":0.33585858,"y":0.8333333},{"x":0.22727273,"y":0.8354701}]},"symbols":[{"text":"சி","confidence":0.9800847},{"text":"த்த","confidence":0.9721509},{"text":"த்தி","confidence":0.99423134},{"property":{"detectedBreak":{"type":"SPACE"}},"text":"ன்","confidence":0.9942114}],"confidence":0.9851696},{"property":{"detectedLanguages":[{"languageCode":"ta","confidence":1}]},"boundingBox":{"normalizedVertices":[{"x":0.3459596,"y":0.80982906},{"x":0.479798,"y":0.8076923},{"x":0.479798,"y":0.8333333},{"x":0.3459596,"y":0.8333333}]},"symbols":[{"text":"ஜ","confidence":0.9878044},{"text":"ட","confidence":0.99471414},{"text":"த்த","confidence":0.9855769},{"property":{"detectedBreak":{"type":"SPACE"}},"text":"ன்மை","confidence":0.9342985}],"confidence":0.9755985},{"property":{"detectedLanguages":[{"languageCode":"ta","confidence":1}]},"boundingBox":{"normalizedVertices":[{"x":0.48232323,"y":0.8076923},{"x":0.57575756,"y":0.8076923},{"x":0.57575756,"y":0.8311966},{"x":0.48232323,"y":0.8333333}]},"symbols":[{"text":"சி","confidence":0.9938331},{"text":"த்தி","confidence":0.9517554},{"text":"லு","confidence":0.9657459},{"property":{"detectedBreak":{"type":"SPACE"}},"text":"ம்","confidence":0.9938324}],"confidence":0.9762917},{"property":{"detectedLanguages":[{"languageCode":"ta","confidence":1}]},"boundingBox":{"normalizedVertices":[{"x":0.5808081,"y":0.8076923},{"x":0.7676768,"y":0.8055556},{"x":0.7676768,"y":0.82905984},{"x":0.5833333,"y":0.8311966}]},"symbols":[{"text":"கா","confidence":0.99415827},{"text":"ண","confidence":0.9957192},{"text":"ப்ப","confidence":0.9907147},{"text":"டு","confidence":0.9907524},{"text":"கி","confidence":0.99125683},{"text":"ன்ற","confidence":0.9831562},{"text":"ன","confidence":0.9926055}],"confidence":0.9911947},{"property":{"detectedLanguages":[{"languageCode":"ta","confidence":1}]},"boundingBox":{"normalizedVertices":[{"x":0.77020204,"y":0.8055556},{"x":0.7752525,"y":0.8055556},{"x":0.7752525,"y":0.82905984},{"x":0.77020204,"y":0.82905984}]},"symbols":[{"property":{"detectedBreak":{"type":"SPACE"}},"text":".","confidence":0.97967464}],"confidence":0.97967464},{"property":{"detectedLanguages":[{"languageCode":"ta","confidence":1}]},"boundingBox":{"normalizedVertices":[{"x":0.7828283,"y":0.8055556},{"x":0.79545456,"y":0.8055556},{"x":0.79545456,"y":0.82905984},{"x":0.78535354,"y":0.82905984}]},"symbols":[{"text":"(","confidence":0.9455213}],"confidence":0.9455213},{"property":{"detectedLanguages":[{"languageCode":"ta","confidence":1}]},"boundingBox":{"normalizedVertices":[{"x":0.79545456,"y":0.8055556},{"x":0.81313133,"y":0.8055556},{"x":0.81313133,"y":0.82905984},{"x":0.79545456,"y":0.82905984}]},"symbols":[{"text":"கூ","confidence":0.7095899}],"confidence":0.7095899},{"property":{"detectedLanguages":[{"languageCode":"ta","confidence":1}]},"boundingBox":{"normalizedVertices":[{"x":0.82575756,"y":0.8034188},{"x":0.84343433,"y":0.8034188},{"x":0.8459596,"y":0.82905984},{"x":0.82575756,"y":0.82905984}]},"symbols":[{"property":{"detectedBreak":{"type":"LINE_BREAK"}},"text":")","confidence":0.7579358}],"confidence":0.7579358}],"confidence":0.97704095}],"blockType":"TEXT","confidence":0.95206916},{"boundingBox":{"normalizedVertices":[{"x":0.5429293,"y":0.8055556},{"x":0.5479798,"y":0.8055556},{"x":0.5479798,"y":0.8076923},{"x":0.5429293,"y":0.8076923}]},"paragraphs":[{"boundingBox":{"normalizedVertices":[{"x":0.5429293,"y":0.8055556},{"x":0.5479798,"y":0.8055556},{"x":0.5479798,"y":0.8076923},{"x":0.5429293,"y":0.8076923}]},"words":[{"boundingBox":{"normalizedVertices":[{"x":0.5429293,"y":0.8055556},{"x":0.5479798,"y":0.8055556},{"x":0.5479798,"y":0.8076923},{"x":0.5429293,"y":0.8076923}]},"symbols":[{"text":"7","confidence":0.31713998},{"property":{"detectedBreak":{"type":"LINE_BREAK"}},"text":"7","confidence":0.7410371}],"confidence":0.5290885}],"confidence":0.5290885}],"blockType":"TEXT","confidence":0.5290885}],"confidence":0.87274057}],"text":"ஸ்ரீ ராமகீதை.\nருஎ\nएकत्र वासात् अनलातलोहवत् चिह्निम्बसाक्षात्मधियाम् प्रसङ्गतः\nचिदात्मचेतसोः अन्योन्यम् अध्यासवशात् जडाजडत्वम् प्रतीयते ॥\n(இ-ள்) ஓரிடத்தில் வசித்தலால் * அநலிற் காய்ந்த\nஇரும்பினைப்போல, சிற்பிரதிபிம்பம் இந்திரியங்களோடுகூ\nடிய மனது அந்தக்கரணம் என்பவற்றின் சமீபமா யிருத்\nதல் காரணமாகச் சிதாத்மாவிலும் (ஜீவனிடத்தும்) சித்தத்\nதும் ஒன்றில் ஒன்றன் அத்தியாசவசத்தால் ஜடத்துவ\nமும் அஜடத்துவமும் தோற்றுகின்றன. (எ-று.)\nசித்தத்திற்கு (விருத்திகளுக்கு) ஞானத்தன்மையும்,\nஜீவாத்மாவிற்கு ஜடத்தன்மையும் தோற்றுகின்றன. இத\nனாற்றான் ஞானாசிரயம் ஆத்மா வென்று தார்க்கிகர் வியவகார\nமும், ஜீவாத்மாவினிடத்து அறிஞர்களால் ஜடாத்மா\nவென்று சொல்லப்படுகின்றது என்று ஸ்மார்த்தர் வியவகா\nரமு முள தாகின்றது.\n(சக)\nगुरोः सकाशादपि वेदवाक्यतः सञ्जातविद्यानुभवो निरीक्ष्य तम् ।\nस्वात्मानमात्मस्थमुपाधिवर्जितं त्यजेदशेषं जडमात्मगोचरम् ॥ ४२ ॥\n* அனலில் இரும்பு காய்ச்சப்பட்டபோது அக்கினியின் எரிக்\nகுந்தன்மை இரும்பிலும், இரும்பின் உருட்சி நீட்சிமுதலியன அக்கி\nனியிலும் காணப்படுவது போல, சித்தின் ஞானத்தன்மை சித்தத்தி\nலும், சித்தத்தின் ஜடத்தன்மை சித்திலும் காணப்படுகின்றன. (கூ)\n77"},"context":{"uri":"gs://iiith-ska-satamt/ocr/src/ramagitai/ramagitai.pdf","pageNumber":65}}]}